Module_2/Week_2/Tasks/Shift_Register/shift_reg.sv
//------------------------------------------------------------------------------
// Module: shift_reg
// Description:
//   This module implements a parameterisable bi-directional serial
//   shift register with active-low reset and enable control, capable
//   of shifting left or right on each rising clock edge while
//   inserting serial input data.
//
// Author      : Muhammad Ahmed Qazi
// Date        : 2025-12-24
// Target      : FPGA
// Clocking    : <clk>, <posedge>
// Reset       : <async>, <active low>
//------------------------------------------------------------------------------

`timescale 1ns/1ps
module shift_reg #(
    // Parameter declaration
    parameter integer DATA_WIDTH = 16
)(
    // Port declarations
    input  wire                     clk,        // Clock input
    input  wire                     rst_n,      // Active-low reset
    input  wire                     shift_en,   // Enable signal
    input  wire                     dir,        // Direction: 0 for left, 1 for right
    input  wire                     d_in,       // Serial input data

    output reg  [DATA_WIDTH-1:0]    q_out       // Parallel output data
);
    // Sequential process block
    always @(posedge clk or negedge rst_n) begin
        if (~rst_n)
            q_out <= {DATA_WIDTH{1'b0}};
        else if (shift_en) begin
            if (dir == 1'b0) // Shift left
                q_out <= {q_out[DATA_WIDTH-2:0], d_in};
            else // Shift right
                q_out <= {d_in, q_out[DATA_WIDTH-1:1]};
        end
        // else: retain current value
    end

endmodule

Module_2/Week_2/Tasks/Shift_Register/shift_reg_tb.sv
`timescale 1ns/1ps

module shift_reg_tb;

    // -------------------------
    // Parameters
    // -------------------------
    localparam int DATA_WIDTH = 8;

    // -------------------------
    // Signals
    // -------------------------
    logic clk;
    logic rst_n;
    logic shift_en;
    logic dir;
    logic d_in;
    logic [DATA_WIDTH-1:0] q_out;

    // Reference model
    logic [DATA_WIDTH-1:0] ref_q;

    // -------------------------
    // DUT instantiation (Layer 1)
    // -------------------------
    shift_reg #(
        .DATA_WIDTH(DATA_WIDTH)
    ) dut (
        .clk      (clk),
        .rst_n    (rst_n),
        .shift_en (shift_en),
        .dir      (dir),
        .d_in     (d_in),
        .q_out    (q_out)
    );

    // -------------------------
    // Clock generator (Layer 2)
    // -------------------------
    always #5 clk <= ~clk;

    // -------------------------
    // Pringing waveform
    // -------------------------
    initial begin
        $dumpfile("shift_reg.vcd");
        $dumpvars(0, shift_reg_tb);
    end

    // -------------------------
    // Reset task (Layer 2)
    // -------------------------
    task apply_reset;
    begin
        rst_n    = 0;
        shift_en = 0;
        dir      = 0;
        d_in     = 0;
        ref_q    = 0;
        repeat (2) @(posedge clk);
        rst_n = 1;
    end
    endtask

    // -------------------------
    // Driver tasks (Layer 3)
    // -------------------------
    task shift_left(input logic din);
    begin
        @(posedge clk);
        shift_en = 1;
        dir = 0;
        d_in = din;
    end
    endtask

    task shift_right(input logic din);
    begin
        @(posedge clk);
        shift_en = 1;
        dir = 1;
        d_in = din;
    end
    endtask

    task hold;
    begin
        @(posedge clk);
        shift_en = 0;
    end
    endtask

    // -------------------------
    // Reference model (Layer 5)
    // -------------------------
    always @(posedge clk or negedge rst_n) begin
        if (!rst_n)
            ref_q <= '0;
        else if (shift_en) begin
            if (dir == 0)
                ref_q <= {ref_q[DATA_WIDTH-2:0], d_in};
            else
                ref_q <= {d_in, ref_q[DATA_WIDTH-1:1]};
        end
    end

    // -------------------------
    // Monitor + checker (Layer 4 + 5)
    // -------------------------
    always @(posedge clk or negedge rst_n) begin
        if (!rst_n) begin
            $display("T=%0t | RESET | q_out=%b (expected 0)",
                    $time, q_out);
        end
        else if (q_out === ref_q) begin
            $display("T=%0t | PASS | en=%b dir=%b din=%b | q_out=%b",
                    $time, shift_en, dir, d_in, q_out);
        end
        else begin
            $display("T=%0t | FAIL | en=%b dir=%b din=%b | DUT=%b REF=%b",
                    $time, shift_en, dir, d_in, q_out, ref_q);
            $error("SHIFT REGISTER MISMATCH");
        end
    end


    // -------------------------
    // Test scenario (Layer 6)
    // -------------------------
    initial begin
        clk = 0;
        apply_reset();

        // Shift left: 1 0 1 1
        shift_left(1);
        shift_left(0);
        shift_left(1);
        shift_left(1);

        hold();
        hold();

        // Shift right: 1 1 0
        shift_right(1);
        shift_right(1);
        shift_right(0);

        #20;
        $finish;
    end

    // Printing waveform
    initial begin
        $dumpfile("shift_reg.vcd");
        $dumpvars(0, shift_reg_tb);
    end

endmodule

Module_2/Week_2/Tasks/Shift_Register/shift_reg.vcd
$version Generated by VerilatedVcd $end
$timescale 1ps $end
 $scope module $rootio $end
 $upscope $end
 $scope module shift_reg_tb $end
  $var wire 32 * DATA_WIDTH [31:0] $end
  $var wire 1 # clk $end
  $var wire 1 $ rst_n $end
  $var wire 1 % shift_en $end
  $var wire 1 & dir $end
  $var wire 1 ' d_in $end
  $var wire 8 ( q_out [7:0] $end
  $var wire 8 ) ref_q [7:0] $end
  $scope module dut $end
   $var wire 32 + DATA_WIDTH [31:0] $end
   $var wire 1 # clk $end
   $var wire 1 $ rst_n $end
   $var wire 1 % shift_en $end
   $var wire 1 & dir $end
   $var wire 1 ' d_in $end
   $var wire 8 ( q_out [7:0] $end
  $upscope $end
 $upscope $end
$enddefinitions $end


#0
0#
0$
0%
0&
0'
b00000000 (
b00000000 )
b00000000000000000000000000001000 *
b00000000000000000000000000001000 +
#5000
1#
#10000
0#
#15000
1#
1$
#20000
0#
#25000
1#
1%
1'
b00000001 (
b00000001 )
#30000
0#
#35000
1#
0'
b00000010 (
b00000010 )
#40000
0#
#45000
1#
1'
b00000101 (
b00000101 )
#50000
0#
#55000
1#
b00001011 (
b00001011 )
#60000
0#
#65000
1#
0%
#70000
0#
#75000
1#
#80000
0#
#85000
1#
1%
1&
b10000101 (
b10000101 )
#90000
0#
#95000
1#
b11000010 (
b11000010 )
#100000
0#
#105000
1#
0'
b01100001 (
b01100001 )
#110000
0#
#115000
1#
b00110000 (
b00110000 )
#120000
0#
#125000
1#
b00011000 (
b00011000 )
