Module_2/Week_2/Tasks/Adder_Tree_Multiplier/adder_tree_multiplier.sv
//------------------------------------------------------------------------------
// Module: adder_tree_multiplier
// Description:
//   Implements a 8x8 combinational multiplier using an adder-tree architecture.
//   Partial products are generated in parallel and reduced through staged
//   additions for improved performance.
//
// Author      : Muhammad Ahmed Qazi
// Date        : 2025-12-26
// Target      : FPGA
// Clocking    : <clk>, <posedge>
// Reset       : <async>, <active low>
//------------------------------------------------------------------------------

module adder_tree_multiplier_top #(
    parameter integer DATA_WIDTH = 8
)(
    input wire                     clk,
    input wire                     rst_n,

    // Input side
    input wire                     EA,     // Enable A register
    input wire                     EB,     // Enable B register
    input wire [DATA_WIDTH-1:0]    A_in,
    input wire [DATA_WIDTH-1:0]    B_in,

    // Output side
    output reg  [2*DATA_WIDTH-1:0]  P_out   
);

    // Input registers
    reg [DATA_WIDTH-1:0] A_reg;
    reg [DATA_WIDTH-1:0] B_reg;

    // Combinational multiplier output
    wire [2*DATA_WIDTH-1:0] product_wire;

    // Input registers
    always @(posedge clk or negedge rst_n) begin
        if (!rst_n) begin
            A_reg <= {DATA_WIDTH{1'b0}};
            B_reg <= {DATA_WIDTH{1'b0}};
        end else begin
            if (EA)
                A_reg <= A_in;
            if (EB)
                B_reg <= B_in;
        end
    end

    // Adder-tree multiplier instance
    adder_tree_multiplier #(
        .DATA_WIDTH(DATA_WIDTH)
    ) u_adder_tree_multiplier (
        .a(A_reg),
        .b(B_reg),
        .product(product_wire)
    );

    // Output register
    always @(posedge clk or negedge rst_n) begin
        if (!rst_n) begin
            P_out <= {(2*DATA_WIDTH){1'b0}};
        end else begin
            P_out <= product_wire;
        end
    end

endmodule

module adder_tree_multiplier #(
    // Parameter declarations
    parameter integer DATA_WIDTH = 8
)(
    // Port declarations
    input  wire [DATA_WIDTH-1:0]    a,
    input  wire [DATA_WIDTH-1:0]    b,
    output wire [2*DATA_WIDTH-1:0]  product
);

    // Partial product (extended to 2N)
    wire [2*DATA_WIDTH-1:0] pp [DATA_WIDTH-1:0];

    genvar i;
    generate
        for (i = 0; i < DATA_WIDTH; i = i + 1) begin : GEN_PP
            assign pp[i] = b[i] ? ({{DATA_WIDTH{1'b0}}, a} << i)
                                : {2*DATA_WIDTH{1'b0}};

        end
    endgenerate

    // Product calculation using adder tree
    wire [2*DATA_WIDTH-1:0] sum_stage1 [((DATA_WIDTH+1)/2)-1:0];
    wire [2*DATA_WIDTH-1:0] sum_stage2 [((DATA_WIDTH+3)/4)-1:0];

    // First stage of addition
    assign sum_stage1[0] = pp[0] + pp[1];
    assign sum_stage1[1] = pp[2] + pp[3];
    assign sum_stage1[2] = pp[4] + pp[5];
    assign sum_stage1[3] = pp[6] + pp[7];

    // Second stage of addition
    assign sum_stage2[0] = sum_stage1[0] + sum_stage1[1];
    assign sum_stage2[1] = sum_stage1[2] + sum_stage1[3];

    // Final addition to get the product
    assign product = sum_stage2[0] + sum_stage2[1];

endmodule

Module_2/Week_2/Tasks/Array_Multiplier/tb_multiplier.sv
module tb_multiplier();

    // =========================================================================
    // SIGNAL DECLARATIONS
    // =========================================================================
    logic                   clk;
    logic                   rst_n;
    logic [7:0]            A_in;
    logic [7:0]            B_in;
    logic                  EA;
    logic                  EB;
    logic [15:0]           P_out;
    
    // Scoreboard signals
    logic [15:0]           expected;
    logic [15:0]           p_val;
    logic [7:0]            a_val, b_val;
    
    // =========================================================================
    // QUEUE DECLARATIONS
    // =========================================================================
    logic [7:0] A_queue [$];
    logic [7:0] B_queue [$];
    
    // =========================================================================
    // PRINTING WAVEFORM
    // =========================================================================
    initial begin
        $dumpfile("tb_multiplier.vcd");
        $dumpvars(0, tb_multiplier);
    end
    
    // =========================================================================
    // DUT INSTANTIATION
    // =========================================================================
    `ifdef ARRAY_MULT
        array_multiplier_top #(
            .DATA_WIDTH(8)
        ) dut (
            .clk(clk),
            .rst_n(rst_n),
            .EA(EA),
            .EB(EB),
            .A_in(A_in),
            .B_in(B_in),
            .P_out(P_out)
        );
    `else
        adder_tree_multiplier_top #(
            .DATA_WIDTH(8)
        ) dut (
            .clk(clk),
            .rst_n(rst_n),
            .EA(EA),
            .EB(EB),
            .A_in(A_in),
            .B_in(B_in),
            .P_out(P_out)
        );
    `endif
    
    // =========================================================================
    // CLOCK GENERATION
    // =========================================================================
    initial begin
        clk = 0;
        forever #5 clk = ~clk;  // 10ns period
    end
    
    // =========================================================================
    // RESET SEQUENCE
    // =========================================================================
    initial begin
        rst_n = 0;
        repeat(3) @(posedge clk);
        rst_n = 1;
    end
    
    // =========================================================================
    // DRIVER PROCESS (Stimulus Application)
    // =========================================================================
    initial begin
        // Wait for reset to deassert
        @(posedge rst_n);
        
        // Test Vector 1: 10 * 15 = 150
        A_in = 8'd10;
        B_in = 8'd15;
        EA = 1;
        EB = 1;
        A_queue.push_back(A_in);
        B_queue.push_back(B_in);
        @(posedge clk);
        EA = 0;
        EB = 0;
        @(posedge clk);
        
        // Test Vector 2: 0 * 255 = 0 (boundary condition)
        A_in = 8'd0;
        B_in = 8'd255;
        EA = 1;
        EB = 1;
        A_queue.push_back(A_in);
        B_queue.push_back(B_in);
        @(posedge clk);
        EA = 0;
        EB = 0;
        @(posedge clk);
        
        // Test Vector 3: 255 * 255 = 65025 (max boundary)
        A_in = 8'd255;
        B_in = 8'd255;
        EA = 1;
        EB = 1;
        A_queue.push_back(A_in);
        B_queue.push_back(B_in);
        @(posedge clk);
        EA = 0;
        EB = 0;
        @(posedge clk);
        
        // Test Vector 4: 128 * 128 = 16384 (power of 2)
        A_in = 8'd128;
        B_in = 8'd128;
        EA = 1;
        EB = 1;
        A_queue.push_back(A_in);
        B_queue.push_back(B_in);
        @(posedge clk);
        EA = 0;
        EB = 0;
        @(posedge clk);
        
        // Signal end of test
        #100;
        $finish;
    end
    
    // =========================================================================
    // SCOREBOARD PROCESS (Self-Checking)
    // =========================================================================
    initial begin
        integer test_num = 0;
        
        // Wait for reset to deassert
        @(posedge rst_n);
        
        // Wait for pipeline to start producing valid outputs
        repeat(2) @(posedge clk);
        
        // Loop through test vectors
        forever begin
            if (A_queue.size() > 0 && B_queue.size() > 0) begin
                // Pop test vector
                a_val = A_queue.pop_front();
                b_val = B_queue.pop_front();
                
                // Calculate expected result
                expected = a_val * b_val;
                
                // Wait for clock edge and sample output
                @(posedge clk);
                p_val = P_out;
                
                // Compare and log
                test_num = test_num + 1;
                if (p_val == expected) begin
                    $display("[PASS] Test %0d: A=%3d, B=%3d | Expected=%5d, Got=%5d", 
                            test_num, a_val, b_val, expected, p_val);
                end else begin
                    $display("[FAIL] Test %0d: A=%3d, B=%3d | Expected=%5d, Got=%5d", 
                            test_num, a_val, b_val, expected, p_val);
                end
                
                @(posedge clk);  // ← ADD THIS: Extra cycle to account for full 2-cycle latency
            end else begin
                @(posedge clk);
            end
        end
    end
    
endmodule

Module_2/Week_2/Tasks/Adder_Tree_Multiplier/tb_multiplier.vcd
$version Generated by VerilatedVcd $end
$timescale 1ps $end
 $scope module $rootio $end
 $upscope $end
 $scope module tb_multiplier $end
  $var wire 1 : clk $end
  $var wire 1 ; rst_n $end
  $var wire 8 < A_in [7:0] $end
  $var wire 8 = B_in [7:0] $end
  $var wire 1 > EA $end
  $var wire 1 ? EB $end
  $var wire 16 ( P_out [15:0] $end
  $var wire 16 # expected [15:0] $end
  $var wire 16 $ p_val [15:0] $end
  $var wire 8 % a_val [7:0] $end
  $var wire 8 & b_val [7:0] $end
  $scope module dut $end
   $var wire 32 @ DATA_WIDTH [31:0] $end
   $var wire 1 : clk $end
   $var wire 1 ; rst_n $end
   $var wire 1 > EA $end
   $var wire 1 ? EB $end
   $var wire 8 < A_in [7:0] $end
   $var wire 8 = B_in [7:0] $end
   $var wire 16 ( P_out [15:0] $end
   $var wire 8 ) A_reg [7:0] $end
   $var wire 8 * B_reg [7:0] $end
   $var wire 16 + product_wire [15:0] $end
   $scope module u_adder_tree_multiplier $end
    $var wire 32 @ DATA_WIDTH [31:0] $end
    $var wire 8 ) a [7:0] $end
    $var wire 8 * b [7:0] $end
    $var wire 16 + product [15:0] $end
    $var wire 16 , pp[0] [15:0] $end
    $var wire 16 - pp[1] [15:0] $end
    $var wire 16 . pp[2] [15:0] $end
    $var wire 16 / pp[3] [15:0] $end
    $var wire 16 0 pp[4] [15:0] $end
    $var wire 16 1 pp[5] [15:0] $end
    $var wire 16 2 pp[6] [15:0] $end
    $var wire 16 3 pp[7] [15:0] $end
    $var wire 16 4 sum_stage1[0] [15:0] $end
    $var wire 16 5 sum_stage1[1] [15:0] $end
    $var wire 16 6 sum_stage1[2] [15:0] $end
    $var wire 16 7 sum_stage1[3] [15:0] $end
    $var wire 16 8 sum_stage2[0] [15:0] $end
    $var wire 16 9 sum_stage2[1] [15:0] $end
   $upscope $end
  $upscope $end
  $scope module unnamedblk1 $end
   $var wire 32 ' test_num [31:0] $end
  $upscope $end
 $upscope $end
$enddefinitions $end


#0
b0000000000000000 #
b0000000000000000 $
b00000000 %
b00000000 &
b00000000000000000000000000000000 '
b0000000000000000 (
b00000000 )
b00000000 *
b0000000000000000 +
b0000000000000000 ,
b0000000000000000 -
b0000000000000000 .
b0000000000000000 /
b0000000000000000 0
b0000000000000000 1
b0000000000000000 2
b0000000000000000 3
b0000000000000000 4
b0000000000000000 5
b0000000000000000 6
b0000000000000000 7
b0000000000000000 8
b0000000000000000 9
0:
0;
b00000000 <
b00000000 =
0>
0?
b00000000000000000000000000001000 @
#5
1:
#10
0:
#15
1:
#20
0:
#25
b00001010 )
b00001111 *
b0000000010010110 +
b0000000000001010 ,
b0000000000010100 -
b0000000000101000 .
b0000000001010000 /
b0000000000011110 4
b0000000001111000 5
b0000000010010110 8
1:
1;
b00001010 <
b00001111 =
1>
1?
#30
0:
#35
b0000000010010110 (
1:
0>
0?
#40
0:
#45
b0000000010010110 #
b00001010 %
b00001111 &
b00000000 )
b11111111 *
b0000000000000000 +
b0000000000000000 ,
b0000000000000000 -
b0000000000000000 .
b0000000000000000 /
b0000000000000000 4
b0000000000000000 5
b0000000000000000 8
1:
b00000000 <
b11111111 =
1>
1?
#50
0:
#55
b0000000010010110 $
b00000000000000000000000000000001 '
b0000000000000000 (
1:
0>
0?
#60
0:
#65
b0000000000000000 #
b00000000 %
b11111111 &
b11111111 )
b1111111000000001 +
b0000000011111111 ,
b0000000111111110 -
b0000001111111100 .
b0000011111111000 /
b0000111111110000 0
b0001111111100000 1
b0011111111000000 2
b0111111110000000 3
b0000001011111101 4
b0000101111110100 5
b0010111111010000 6
b1011111101000000 7
b0000111011110001 8
b1110111100010000 9
1:
b11111111 <
1>
1?
#70
0:
#75
b0000000000000000 $
b00000000000000000000000000000010 '
b1111111000000001 (
1:
0>
0?
#80
0:
#85
b1111111000000001 #
b11111111 %
b10000000 )
b10000000 *
b0100000000000000 +
b0000000000000000 ,
b0000000000000000 -
b0000000000000000 .
b0000000000000000 /
b0000000000000000 0
b0000000000000000 1
b0000000000000000 2
b0100000000000000 3
b0000000000000000 4
b0000000000000000 5
b0000000000000000 6
b0100000000000000 7
b0000000000000000 8
b0100000000000000 9
1:
b10000000 <
b10000000 =
1>
1?
#90
0:
#95
b1111111000000001 $
b00000000000000000000000000000011 '
b0100000000000000 (
1:
0>
0?
#100
0:
#105
b0100000000000000 #
b10000000 %
b10000000 &
1:
#110
0:
#115
b0100000000000000 $
b00000000000000000000000000000100 '
1:
