Module 2/Week 1/Tasks/Barrel Shifter/barrel_shifter.sv
//------------------------------------------------------------------------------
// Module: 32-bit Barrel Shifter
// Description:
//   This is a 32-bit Barrel Shifter module that performs
//   logical left and right shifts based on the control signals.
//
// Author      : Muhammad Ahmed Qazi
// Date        : 2025-12-16
//------------------------------------------------------------------------------

module barrel_shifter_32bit #(
	
	// Parameter declarations
	parameter integer DATA_WIDTH = 32,
    parameter integer SHIFT_WIDTH = 5
	)(
	
	// Port declarations
	input   [DATA_WIDTH - 1:0]  data_in,
    input   [SHIFT_WIDTH - 1:0] shift_amount,
    input                       dir,
	
    output  [DATA_WIDTH - 1:0]  data_out
    );

	// Internal signals for stage outputs
    wire [DATA_WIDTH - 1:0] stage0_out;
    wire [DATA_WIDTH - 1:0] stage1_out;
    wire [DATA_WIDTH - 1:0] stage2_out;
    wire [DATA_WIDTH - 1:0] stage3_out;
    wire [DATA_WIDTH - 1:0] stage4_out;

	// Combinatinonal Logic
	
    // Stage 0: Shift by 1
    assign stage0_out = shift_amount[0] ? 
                        (dir ? {data_in[DATA_WIDTH - 2:0], 1'b0} : {1'b0, data_in[DATA_WIDTH - 1:1]}) : 
                        data_in;
    
    // Stage 1: Shift by 2
    assign stage1_out = shift_amount[1] ? 
                        (dir ? {stage0_out[DATA_WIDTH - 3:0], 2'b00} : {2'b00, stage0_out[DATA_WIDTH - 1:2]}) : 
                        stage0_out;

    // Stage 2: Shift by 4
    assign stage2_out = shift_amount[2] ? 
                        (dir ? {stage1_out[DATA_WIDTH - 5:0], 4'b0000} : {4'b0000, stage1_out[DATA_WIDTH - 1:4]}) : 
                        stage1_out;

    // Stage 3: Shift by 8
    assign stage3_out = shift_amount[3] ? 
                        (dir ? {stage2_out[DATA_WIDTH - 9:0], 8'b00000000} : {8'b00000000, stage2_out[DATA_WIDTH - 1:8]}) : 
                        stage2_out;
    
    // Stage 4: Shift by 16
    assign stage4_out = shift_amount[4] ? 
                        (dir ? {stage3_out[DATA_WIDTH - 17:0], 16'b0000000000000000} : {16'b0000000000000000, stage3_out[DATA_WIDTH - 1:16]}) : 
                        stage3_out;
    
    // Final output
    assign data_out = stage4_out;

endmodule

Module 2/Week 1/Tasks/Barrel Shifter/barrel_shifter_tb.sv
`timescale 1ns/1ps

module barrel_shifter_tb;

    // Testbench signals
    reg  [31:0] data_in;
    reg  [4:0]  shift_amount;
    reg         dir;       // 0=left, 1=right
    wire [31:0] data_out;

    // Instantiate DUT
    barrel_shifter_32bit dut (
        .data_in      (data_in),
        .shift_amount (shift_amount),
        .dir          (dir),
        .data_out     (data_out)
    );

    // Counters
    integer total_tests = 0;
    integer passed_tests = 0;

    // Task to compute staged expected output and check DUT
    task check_shift;
        input [31:0] test_data;
        input [4:0]  test_shift;
        input        test_dir;
        reg [31:0] stage0, stage1, stage2, stage3, stage4;
        reg [31:0] expected;
        begin
            data_in      = test_data;
            shift_amount = test_shift;
            dir          = test_dir;
            #1; // small delay for combinational logic

            // Stage 0: shift by 1
            stage0 = test_shift[0] ? (test_dir ? {test_data[30:0], 1'b0} : {1'b0, test_data[31:1]}) : test_data;
            // Stage 1: shift by 2
            stage1 = test_shift[1] ? (test_dir ? {stage0[29:0], 2'b00} : {2'b00, stage0[31:2]}) : stage0;
            // Stage 2: shift by 4
            stage2 = test_shift[2] ? (test_dir ? {stage1[27:0], 4'b0000} : {4'b0000, stage1[31:4]}) : stage1;
            // Stage 3: shift by 8
            stage3 = test_shift[3] ? (test_dir ? {stage2[23:0], 8'b00000000} : {8'b00000000, stage2[31:8]}) : stage2;
            // Stage 4: shift by 16
            stage4 = test_shift[4] ? (test_dir ? {stage3[15:0], 16'b0000000000000000} : {16'b0000000000000000, stage3[31:16]}) : stage3;

            expected = stage4;

            total_tests = total_tests + 1;

            if (data_out === expected) begin
                $display("TEST %0d PASS: data_in=%h shift=%0d dir=%b data_out=%h", 
                          total_tests, data_in, shift_amount, dir, data_out);
                passed_tests = passed_tests + 1;
            end else begin
                $display("TEST %0d FAIL: data_in=%h shift=%0d dir=%b data_out=%h (expected %h)", 
                          total_tests, data_in, shift_amount, dir, data_out, expected);
            end
        end
    endtask

    // Printing waveform
     initial begin
         $dumpfile("barrel_shifter.vcd");
         $dumpvars(0, barrel_shifter_tb);
     end

    integer i;
    reg [31:0] rand_data;
    reg [4:0]  rand_shift;
    reg        rand_dir;

    initial begin
        $display("----- Starting 32-bit Barrel Shifter Self-Checking Testbench -----");

        // ----- Directed tests -----
        check_shift(32'h0000_0001, 1, 0);  // left shift by 1
        check_shift(32'h0000_0001, 1, 1);  // right shift by 1
        check_shift(32'h8000_0000, 31, 0); // left shift max
        check_shift(32'h0000_0001, 31, 1); // right shift max
        check_shift(32'hFFFF_FFFF, 16, 0); // left shift all ones
        check_shift(32'hFFFF_FFFF, 16, 1); // right shift all ones
        check_shift(32'h1234_5678, 4, 0);  // left
        check_shift(32'h1234_5678, 4, 1);  // right

        // ----- Randomized tests -----
        for (i = 0; i < 50; i = i + 1) begin
            rand_data  = $random;
            rand_shift = $random % 32;
            rand_dir   = $random % 2;
            check_shift(rand_data, rand_shift, rand_dir);
        end

        // ----- Summary -----
        $display("----- Testbench Summary -----");
        $display("Total tests run : %0d", total_tests);
        $display("Tests passed    : %0d", passed_tests);
        $display("Tests failed    : %0d", total_tests - passed_tests);
        $finish;
    end

endmodule

Module 2/Week 1/Tasks/Barrel Shifter/barrel_shifter.vcd
$date
	Thu Dec 18 15:02:14 2025
$end
$version
	Icarus Verilog
$end
$timescale
	1ps
$end
$scope module barrel_shifter_tb $end
$var wire 32 ! data_out [31:0] $end
$var reg 32 " data_in [31:0] $end
$var reg 1 # dir $end
$var reg 32 $ rand_data [31:0] $end
$var reg 1 % rand_dir $end
$var reg 5 & rand_shift [4:0] $end
$var reg 5 ' shift_amount [4:0] $end
$var integer 32 ( i [31:0] $end
$var integer 32 ) passed_tests [31:0] $end
$var integer 32 * total_tests [31:0] $end
$scope module dut $end
$var wire 32 + data_in [31:0] $end
$var wire 32 , data_out [31:0] $end
$var wire 1 # dir $end
$var wire 5 - shift_amount [4:0] $end
$var wire 32 . stage4_out [31:0] $end
$var wire 32 / stage3_out [31:0] $end
$var wire 32 0 stage2_out [31:0] $end
$var wire 32 1 stage1_out [31:0] $end
$var wire 32 2 stage0_out [31:0] $end
$var parameter 32 3 DATA_WIDTH $end
$var parameter 32 4 SHIFT_WIDTH $end
$upscope $end
$scope task check_shift $end
$var reg 32 5 expected [31:0] $end
$var reg 32 6 stage0 [31:0] $end
$var reg 32 7 stage1 [31:0] $end
$var reg 32 8 stage2 [31:0] $end
$var reg 32 9 stage3 [31:0] $end
$var reg 32 : stage4 [31:0] $end
$var reg 32 ; test_data [31:0] $end
$var reg 1 < test_dir $end
$var reg 5 = test_shift [4:0] $end
$upscope $end
$upscope $end
$enddefinitions $end
$comment Show the parameter values. $end
$dumpall
b101 4
b100000 3
$end
#0
$dumpvars
b1 =
0<
b1 ;
bx :
bx 9
bx 8
bx 7
bx 6
bx 5
b0 2
b0 1
b0 0
b0 /
b0 .
b1 -
b0 ,
b1 +
b0 *
b0 )
bx (
b1 '
bx &
x%
bx $
0#
b1 "
b0 !
$end
#1000
b10 !
b10 ,
b10 .
b10 /
b10 0
b10 1
b10 2
1#
1<
b1 )
b1 *
b0 5
b0 :
b0 9
b0 8
b0 7
b0 6
#2000
b1000000000000000000000000000000 2
b10000000000000000000000000000 1
b1000000000000000000000000 0
b10000000000000000 /
b1 !
b1 ,
b1 .
0#
b11111 '
b11111 -
b10000000000000000000000000000000 "
b10000000000000000000000000000000 +
0<
b11111 =
b10000000000000000000000000000000 ;
b10 )
b10 *
b10 5
b10 :
b10 9
b10 8
b10 7
b10 6
#3000
b10 2
b1000 1
b10000000 0
b1000000000000000 /
b10000000000000000000000000000000 !
b10000000000000000000000000000000 ,
b10000000000000000000000000000000 .
1#
b1 "
b1 +
1<
b1 ;
b11 )
b11 *
b1 5
b1 :
b10000000000000000 9
b1000000000000000000000000 8
b10000000000000000000000000000 7
b1000000000000000000000000000000 6
#4000
b1111111111111111 !
b1111111111111111 ,
b1111111111111111 .
b11111111111111111111111111111111 2
b11111111111111111111111111111111 1
b11111111111111111111111111111111 0
b11111111111111111111111111111111 /
0#
b10000 '
b10000 -
b11111111111111111111111111111111 "
b11111111111111111111111111111111 +
0<
b10000 =
b11111111111111111111111111111111 ;
b100 )
b100 *
b10000000000000000000000000000000 5
b10000000000000000000000000000000 :
b1000000000000000 9
b10000000 8
b1000 7
b10 6
#5000
b11111111111111110000000000000000 !
b11111111111111110000000000000000 ,
b11111111111111110000000000000000 .
1#
1<
b101 )
b101 *
b1111111111111111 5
b1111111111111111 :
b11111111111111111111111111111111 9
b11111111111111111111111111111111 8
b11111111111111111111111111111111 7
b11111111111111111111111111111111 6
#6000
b1001000110100010101100111 /
b1001000110100010101100111 0
b1001000110100010101100111 !
b1001000110100010101100111 ,
b1001000110100010101100111 .
b10010001101000101011001111000 1
b10010001101000101011001111000 2
0#
b100 '
b100 -
b10010001101000101011001111000 "
b10010001101000101011001111000 +
0<
b100 =
b10010001101000101011001111000 ;
b110 )
b110 *
b11111111111111110000000000000000 5
b11111111111111110000000000000000 :
#7000
b100011010001010110011110000000 !
b100011010001010110011110000000 ,
b100011010001010110011110000000 .
b100011010001010110011110000000 /
b100011010001010110011110000000 0
1#
1<
b111 )
b111 *
b1001000110100010101100111 5
b1001000110100010101100111 :
b1001000110100010101100111 9
b1001000110100010101100111 8
b10010001101000101011001111000 7
b10010001101000101011001111000 6
#8000
b100100001010100110101001001000 !
b100100001010100110101001001000 ,
b100100001010100110101001001000 .
b100100001010100110101001001000 /
b100100001010100110101001001000 0
b100100001010100110101001001000 1
b100100001010100110101001001000 2
b1 '
b1 -
b10010000101010011010100100100 "
b10010000101010011010100100100 +
b1 =
b10010000101010011010100100100 ;
1%
b1 &
b10010000101010011010100100100 $
b0 (
b1000 )
b1000 *
b100011010001010110011110000000 5
b100011010001010110011110000000 :
b100011010001010110011110000000 9
b100011010001010110011110000000 8
#9000
b1100011111000001010110011000110 1
b1010110011000110000000000000 !
b1010110011000110000000000000 ,
b1010110011000110000000000000 .
b1100011111000001010110011000110 2
b111110000010101100110001100000 0
b1010110011000110000000000000 /
b1101 '
b1101 -
b10110001111100000101011001100011 "
b10110001111100000101011001100011 +
b1101 =
b10110001111100000101011001100011 ;
b1101 &
b10110001111100000101011001100011 $
b1 (
b1001 )
b1001 *
b100100001010100110101001001000 5
b100100001010100110101001001000 :
b100100001010100110101001001000 9
b100100001010100110101001001000 8
b100100001010100110101001001000 7
b100100001010100110101001001000 6
#10000
b10110010110000101000010001100101 2
b11001011000010100001000110010100 1
b11001011000010100001000110010100 0
b11001011000010100001000110010100 /
b10001100101000000000000000000 !
b10001100101000000000000000000 ,
b10001100101000000000000000000 .
b10010 '
b10010 -
b10110010110000101000010001100101 "
b10110010110000101000010001100101 +
b10010 =
b10110010110000101000010001100101 ;
b10010 &
b10110010110000101000010001100101 $
b10 (
b1010 )
b1010 *
b1010110011000110000000000000 5
b1010110011000110000000000000 :
b1010110011000110000000000000 9
b111110000010101100110001100000 8
b1100011111000001010110011000110 7
b1100011111000001010110011000110 6
#11000
b1000011010000000000000000000000 !
b1000011010000000000000000000000 ,
b1000011010000000000000000000000 .
b11011010111110011010000110100 1
b10110101111100110100001101000000 /
b10110101111100110100001101000000 0
b110110101111100110100001101 2
b10110 '
b10110 -
b110110101111100110100001101 "
b110110101111100110100001101 +
b10110 =
b110110101111100110100001101 ;
b10110 &
b110110101111100110100001101 $
b11 (
b1011 )
b1011 *
b10001100101000000000000000000 5
b10001100101000000000000000000 :
b11001011000010100001000110010100 9
b11001011000010100001000110010100 8
b11001011000010100001000110010100 7
b10110010110000101000010001100101 6
#12000
b1101101010001010111111011010000 0
b1110110110101000101011111101101 1
b1000101011111101101000000000000 /
b1000101011111101101000000000000 !
b1000101011111101101000000000000 ,
b1000101011111101101000000000000 .
b1110110110101000101011111101101 2
b1100 '
b1100 -
b1110110110101000101011111101101 "
b1110110110101000101011111101101 +
b1100 =
b1110110110101000101011111101101 ;
b1100 &
b1110110110101000101011111101101 $
b100 (
b1100 )
b1100 *
b1000011010000000000000000000000 5
b1000011010000000000000000000000 :
b10110101111100110100001101000000 9
b10110101111100110100001101000000 8
b11011010111110011010000110100 7
b110110101111100110100001101 6
#13000
b111000110011011100100100110 !
b111000110011011100100100110 ,
b111000110011011100100100110 .
b111000110011011100100100110 0
b111000110011011100100100110 /
b1110001100110111001001001100011 1
b1110001100110111001001001100011 2
0#
b101 '
b101 -
b11100011001101110010010011000110 "
b11100011001101110010010011000110 +
0<
b101 =
b11100011001101110010010011000110 ;
0%
b101 &
b11100011001101110010010011000110 $
b101 (
b1101 )
b1101 *
b1000101011111101101000000000000 5
b1000101011111101101000000000000 :
b1000101011111101101000000000000 9
b1101101010001010111111011010000 8
b1110110110101000101011111101101 7
b1110110110101000101011111101101 6
#14000
b111001010101111111101111 /
b111001010101111111101111 0
b111001010101111111101111110010 2
b1110010101011111111011111100 1
b11100101 !
b11100101 ,
b11100101 .
b10111 '
b10111 -
b1110010101011111111011111100101 "
b1110010101011111111011111100101 +
b10111 =
b1110010101011111111011111100101 ;
b10111 &
b1110010101011111111011111100101 $
b110 (
b1110 )
b1110 *
b111000110011011100100100110 5
b111000110011011100100100110 :
b111000110011011100100100110 9
b111000110011011100100100110 8
b1110001100110111001001001100011 7
b1110001100110111001001001100011 6
#15000
b1000111111011 !
b1000111111011 ,
b1000111111011 .
b10001111110110011011011100011 1
b10001111110110011011011100011 /
b1000111111011001101101110001111 2
b10001111110110011011011100011 0
b10010 '
b10010 -
b1000111111011001101101110001111 "
b1000111111011001101101110001111 +
b10010 =
b1000111111011001101101110001111 ;
b10010 &
b1000111111011001101101110001111 $
b111 (
b1111 )
b1111 *
b11100101 5
b11100101 :
b111001010101111111101111 9
b111001010101111111101111 8
b1110010101011111111011111100 7
b111001010101111111101111110010 6
#16000
b111101000000000001111010111 /
b1111010000000000011110101110100 1
b111101000000000001111010111 0
b111101000000000001111010111 !
b111101000000000001111010111 ,
b111101000000000001111010111 .
b1111010000000000011110101110100 2
b101 '
b101 -
b11110100000000000111101011101000 "
b11110100000000000111101011101000 +
b101 =
b11110100000000000111101011101000 ;
b101 &
b11110100000000000111101011101000 $
b1000 (
b10000 )
b10000 *
b1000111111011 5
b1000111111011 :
b10001111110110011011011100011 9
b10001111110110011011011100011 8
b10001111110110011011011100011 7
b1000111111011001101101110001111 6
#17000
b10111101000111000101000101111010 1
b11000101000101111010000000000000 !
b11000101000101111010000000000000 ,
b11000101000101111010000000000000 .
b10111101000111000101000101111010 2
b11010001110001010001011110100000 0
b11000101000101111010000000000000 /
1#
b1101 '
b1101 -
b11011110100011100010100010111101 "
b11011110100011100010100010111101 +
1<
b1101 =
b11011110100011100010100010111101 ;
1%
b1101 &
b11011110100011100010100010111101 $
b1001 (
b10001 )
b10001 *
b111101000000000001111010111 5
b111101000000000001111010111 :
b111101000000000001111010111 9
b111101000000000001111010111 8
b1111010000000000011110101110100 7
b1111010000000000011110101110100 6
#18000
b1011000111101111011000 !
b1011000111101111011000 ,
b1011000111101111011000 .
b1011000111101111011000 /
b10110001111011110110001001100011 2
b101100011110111101100010011000 1
b101100011110111101100010011000 0
0#
b1010 '
b1010 -
b10110001111011110110001001100011 "
b10110001111011110110001001100011 +
0<
b1010 =
b10110001111011110110001001100011 ;
0%
b1010 &
b10110001111011110110001001100011 $
b1010 (
b10010 )
b10010 *
b11000101000101111010000000000000 5
b11000101000101111010000000000000 :
b11000101000101111010000000000000 9
b11010001110001010001011110100000 8
b10111101000111000101000101111010 7
b10111101000111000101000101111010 6
#19000
b1000001100100001000010010000000 0
b10010000100001001000000000000000 !
b10010000100001001000000000000000 ,
b10010000100001001000000000000000 .
b1000001100100001000010010000000 1
b10010000100001001000000000000000 /
b10000011001000010000100100000 2
1#
b10000011001000010000100100000 "
b10000011001000010000100100000 +
1<
b10000011001000010000100100000 ;
1%
b10000011001000010000100100000 $
b1011 (
b10011 )
b10011 *
b1011000111101111011000 5
b1011000111101111011000 :
b1011000111101111011000 9
b101100011110111101100010011000 8
b101100011110111101100010011000 7
b10110001111011110110001001100011 6
#20000
b1011001000000011111010010110000 0
b1011001000000011111010010110000 1
b1011001000000011111010010110000 /
b11110100101100000000000000000000 !
b11110100101100000000000000000000 ,
b11110100101100000000000000000000 .
b10010110010000000111110100101100 2
b10011 '
b10011 -
b11001011001000000011111010010110 "
b11001011001000000011111010010110 +
b10011 =
b11001011001000000011111010010110 ;
b10011 &
b11001011001000000011111010010110 $
b1100 (
b10100 )
b10100 *
b10010000100001001000000000000000 5
b10010000100001001000000000000000 :
b10010000100001001000000000000000 9
b1000001100100001000010010000000 8
b1000001100100001000010010000000 7
b10000011001000010000100100000 6
#21000
b1001101001111101011001010011000 0
b1001101001111101011001010011000 1
b1010011010011111010110010100110 2
b111110101100101001100000000000 /
b111110101100101001100000000000 !
b111110101100101001100000000000 ,
b111110101100101001100000000000 .
b1011 '
b1011 -
b10101001101001111101011001010011 "
b10101001101001111101011001010011 +
b1011 =
b10101001101001111101011001010011 ;
b1011 &
b10101001101001111101011001010011 $
b1101 (
b10101 )
b10101 *
b11110100101100000000000000000000 5
b11110100101100000000000000000000 :
b1011001000000011111010010110000 9
b1011001000000011111010010110000 8
b1011001000000011111010010110000 7
b10010110010000000111110100101100 6
#22000
b11010010100000001000000000000000 !
b11010010100000001000000000000000 ,
b11010010100000001000000000000000 .
b100010111010010100000001000 1
b11010010100000001000000000000000 /
b10000001000101110100101000000010 2
b1000101110100101000000010000000 0
b1110 '
b1110 -
b10000001000101110100101000000010 "
b10000001000101110100101000000010 +
b1110 =
b10000001000101110100101000000010 ;
b1110 &
b10000001000101110100101000000010 $
b1110 (
b10110 )
b10110 *
b111110101100101001100000000000 5
b111110101100101001100000000000 :
b111110101100101001100000000000 9
b1001101001111101011001010011000 8
b1001101001111101011001010011000 7
b1010011010011111010110010100110 6
#23000
b11100111110001010111001011001 !
b11100111110001010111001011001 ,
b11100111110001010111001011001 .
b11100111110001010111001011001 1
b11100111110001010111001011001 0
b11100111110001010111001011001 /
b1110011111000101011100101100111 2
0#
b11 '
b11 -
b11100111110001010111001011001111 "
b11100111110001010111001011001111 +
0<
b11 =
b11100111110001010111001011001111 ;
0%
b11 &
b11100111110001010111001011001111 $
b1111 (
b10111 )
b10111 *
b11010010100000001000000000000000 5
b11010010100000001000000000000000 :
b11010010100000001000000000000000 9
b1000101110100101000000010000000 8
b100010111010010100000001000 7
b10000001000101110100101000000010 6
#24000
b11100101011100110000101011001010 2
b11100101011100110000101011001010 1
b1110010101110011000010101100 0
b11100101011100110000 /
b1110 !
b1110 ,
b1110 .
b11100 '
b11100 -
b11100101011100110000101011001010 "
b11100101011100110000101011001010 +
b11100 =
b11100101011100110000101011001010 ;
b11100 &
b11100101011100110000101011001010 $
b10000 (
b11000 )
b11000 *
b11100111110001010111001011001 5
b11100111110001010111001011001 :
b11100111110001010111001011001 9
b11100111110001010111001011001 8
b11100111110001010111001011001 7
b1110011111000101011100101100111 6
#25000
b100010100101110011000011000101 0
b100010100101110011000011000101 /
b100010100101110011000011000101 !
b100010100101110011000011000101 ,
b100010100101110011000011000101 .
b100010100101110011000011000101 1
b100010100101110011000011000101 2
b1 '
b1 -
b1000101001011100110000110001010 "
b1000101001011100110000110001010 +
b1 =
b1000101001011100110000110001010 ;
b1 &
b1000101001011100110000110001010 $
b10001 (
b11001 )
b11001 *
b1110 5
b1110 :
b11100101011100110000 9
b1110010101110011000010101100 8
b11100101011100110000101011001010 7
b11100101011100110000101011001010 6
#26000
b1111000010000011110011011110000 0
b1111000010000011110011011110000 1
b1000001111001101111000000000000 !
b1000001111001101111000000000000 ,
b1000001111001101111000000000000 .
b1111000010000011110011011110000 2
b1000001111001101111000000000000 /
1#
b1001 '
b1001 -
b111100001000001111001101111000 "
b111100001000001111001101111000 +
1<
b1001 =
b111100001000001111001101111000 ;
1%
b1001 &
b111100001000001111001101111000 $
b10010 (
b11010 )
b11010 *
b100010100101110011000011000101 5
b100010100101110011000011000101 :
b100010100101110011000011000101 9
b100010100101110011000011000101 8
b100010100101110011000011000101 7
b100010100101110011000011000101 6
#27000
b1011011000000100110010110 !
b1011011000000100110010110 ,
b1011011000000100110010110 .
b1011011000000100110010110110110 2
b10110110000001001100101101101 1
b1011011000000100110010110 0
b1011011000000100110010110 /
0#
b110 '
b110 -
b1011011000000100110010110110110 "
b1011011000000100110010110110110 +
0<
b110 =
b1011011000000100110010110110110 ;
0%
b110 &
b1011011000000100110010110110110 $
b10011 (
b11011 )
b11011 *
b1000001111001101111000000000000 5
b1000001111001101111000000000000 :
b1000001111001101111000000000000 9
b1111000010000011110011011110000 8
b1111000010000011110011011110000 7
b1111000010000011110011011110000 6
#28000
b11010100000010101111000000000000 !
b11010100000010101111000000000000 ,
b11010100000010101111000000000000 .
b1111001110101000000101011110000 1
b1111001110101000000101011110000 0
b11010100000010101111000000000000 /
b11011110011101010000001010111100 2
1#
b1010 '
b1010 -
b11011110011101010000001010111100 "
b11011110011101010000001010111100 +
1<
b1010 =
b11011110011101010000001010111100 ;
1%
b1010 &
b11011110011101010000001010111100 $
b10100 (
b11100 )
b11100 *
b1011011000000100110010110 5
b1011011000000100110010110 :
b1011011000000100110010110 9
b1011011000000100110010110 8
b10110110000001001100101101101 7
b1011011000000100110010110110110 6
#29000
b10010111101111100111000100000 !
b10010111101111100111000100000 ,
b10010111101111100111000100000 .
b1110001001011110111110011100010 1
b10010111101111100111000100000 0
b10010111101111100111000100000 /
b1110001001011110111110011100010 2
b101 '
b101 -
b10111000100101111011111001110001 "
b10111000100101111011111001110001 +
b101 =
b10111000100101111011111001110001 ;
b101 &
b10111000100101111011111001110001 $
b10101 (
b11101 )
b11101 *
b11010100000010101111000000000000 5
b11010100000010101111000000000000 :
b11010100000010101111000000000000 9
b1111001110101000000101011110000 8
b1111001110101000000101011110000 7
b11011110011101010000001010111100 6
#30000
b10011101110011000110000000111011 2
b100111011100110001100000001110 1
b100111011100110001100000001110 0
b1001110111001100011000 /
b100111 !
b100111 ,
b100111 .
0#
b11010 '
b11010 -
b10011101110011000110000000111011 "
b10011101110011000110000000111011 +
0<
b11010 =
b10011101110011000110000000111011 ;
0%
b11010 &
b10011101110011000110000000111011 $
b10110 (
b11110 )
b11110 *
b10010111101111100111000100000 5
b10010111101111100111000100000 :
b10010111101111100111000100000 9
b10010111101111100111000100000 8
b1110001001011110111110011100010 7
b1110001001011110111110011100010 6
#31000
b10101010101001001011000101010 0
b10010110001010100000000000000000 !
b10010110001010100000000000000000 ,
b10010110001010100000000000000000 .
b10101010101001001011000101010 1
b10101010101001001011000101010 /
b10101010101001001011000101010 2
1#
b10001 '
b10001 -
b1010101010100100101100010101 "
b1010101010100100101100010101 +
1<
b10001 =
b1010101010100100101100010101 ;
1%
b10001 &
b1010101010100100101100010101 $
b10111 (
b11111 )
b11111 *
b100111 5
b100111 :
b1001110111001100011000 9
b100111011100110001100000001110 8
b100111011100110001100000001110 7
b10011101110011000110000000111011 6
#32000
b110001001000110000011101100010 1
b110001001000110000011101100010 2
b10010001100000111011000100000 0
b110000011101100010000000000000 /
b110000011101100010000000000000 !
b110000011101100010000000000000 ,
b110000011101100010000000000000 .
b1100 '
b1100 -
b110001001000110000011101100010 "
b110001001000110000011101100010 +
b1100 =
b110001001000110000011101100010 ;
b1100 &
b110001001000110000011101100010 $
b11000 (
b100000 )
b100000 *
b10010110001010100000000000000000 5
b10010110001010100000000000000000 :
b10101010101001001011000101010 9
b10101010101001001011000101010 8
b10101010101001001011000101010 7
b10101010101001001011000101010 6
#33000
b10111001101000011000111100000000 /
b1000111101110011010000110001111 0
b10001111000000000000000000000000 !
b10001111000000000000000000000000 ,
b10001111000000000000000000000000 .
b1000111101110011010000110001111 1
b1000111101110011010000110001111 2
b11000 '
b11000 -
b1000111101110011010000110001111 "
b1000111101110011010000110001111 +
b11000 =
b1000111101110011010000110001111 ;
b11000 &
b1000111101110011010000110001111 $
b11001 (
b100001 )
b100001 *
b110000011101100010000000000000 5
b110000011101100010000000000000 :
b110000011101100010000000000000 9
b10010001100000111011000100000 8
b110001001000110000011101100010 7
b110001001000110000011101100010 6
#34000
b11110000000000000000000000000000 !
b11110000000000000000000000000000 ,
b11110000000000000000000000000000 .
b1000101011010011111000000000000 /
b11111100010001010110100111110000 0
b11001111110001000101011010011111 1
b11001111110001000101011010011111 2
b11100 '
b11100 -
b11001111110001000101011010011111 "
b11001111110001000101011010011111 +
b11100 =
b11001111110001000101011010011111 ;
b11100 &
b11001111110001000101011010011111 $
b11010 (
b100010 )
b100010 *
b10001111000000000000000000000000 5
b10001111000000000000000000000000 :
b10111001101000011000111100000000 9
b1000111101110011010000110001111 8
b1000111101110011010000110001111 7
b1000111101110011010000110001111 6
#35000
b1000100110111100011011 /
b100010011011110001101111000100 0
b1000100110111100011011 !
b1000100110111100011011 ,
b1000100110111100011011 .
b100010011011110001101111000100 1
b100010011011110001101111000100 2
0#
b1001 '
b1001 -
b1000100110111100011011110001001 "
b1000100110111100011011110001001 +
0<
b1001 =
b1000100110111100011011110001001 ;
0%
b1001 &
b1000100110111100011011110001001 $
b11011 (
b100011 )
b100011 *
b11110000000000000000000000000000 5
b11110000000000000000000000000000 :
b1000101011010011111000000000000 9
b11111100010001010110100111110000 8
b11001111110001000101011010011111 7
b11001111110001000101011010011111 6
#36000
b1110101111111110110000001101011 0
b1110101111111110110000001101011 1
b1110101111111110110000001101011 2
b1110101111111110110000001101011 /
b111010111111111 !
b111010111111111 ,
b111010111111111 .
b10001 '
b10001 -
b11101011111111101100000011010111 "
b11101011111111101100000011010111 +
b10001 =
b11101011111111101100000011010111 ;
b10001 &
b11101011111111101100000011010111 $
b11100 (
b100100 )
b100100 *
b1000100110111100011011 5
b1000100110111100011011 :
b1000100110111100011011 9
b100010011011110001101111000100 8
b100010011011110001101111000100 7
b100010011011110001101111000100 6
#37000
b1100001110101111111000011 /
b1100001110101111111000011 0
b110000111010111111100001100 2
b1100001110101111111000011 1
b1100001110101111111000011 !
b1100001110101111111000011 ,
b1100001110101111111000011 .
b10 '
b10 -
b110000111010111111100001100 "
b110000111010111111100001100 +
b10 =
b110000111010111111100001100 ;
b10 &
b110000111010111111100001100 $
b11101 (
b100101 )
b100101 *
b111010111111111 5
b111010111111111 :
b1110101111111110110000001101011 9
b1110101111111110110000001101011 8
b1110101111111110110000001101011 7
b1110101111111110110000001101011 6
#38000
b1011101110000010010110100111011 1
b101110111000001001011010011 0
b1011101110000010010 /
b101 !
b101 ,
b101 .
b1011101110000010010110100111011 2
b11101 '
b11101 -
b10111011100000100101101001110111 "
b10111011100000100101101001110111 +
b11101 =
b10111011100000100101101001110111 ;
b11101 &
b10111011100000100101101001110111 $
b11110 (
b100110 )
b100110 *
b1100001110101111111000011 5
b1100001110101111111000011 :
b1100001110101111111000011 9
b1100001110101111111000011 8
b1100001110101111111000011 7
b110000111010111111100001100 6
#39000
b1111110000010100000000011111100 1
b1111110000010100000000011111100 2
b11100000101000000000111111000000 0
b10100000000011111100000000000000 /
b10100000000011111100000000000000 !
b10100000000011111100000000000000 ,
b10100000000011111100000000000000 .
1#
b1101 '
b1101 -
b10111111000001010000000001111110 "
b10111111000001010000000001111110 +
1<
b1101 =
b10111111000001010000000001111110 ;
1%
b1101 &
b10111111000001010000000001111110 $
b11111 (
b100111 )
b100111 *
b101 5
b101 :
b1011101110000010010 9
b101110111000001001011010011 8
b1011101110000010010110100111011 7
b1011101110000010010110100111011 6
#40000
b11111101001010001111000111110 2
b1111110100101000111100011111000 1
b1111110100101000111100011111000 0
b1111110100101000111100011111000 /
b1111000111110000000000000000000 !
b1111000111110000000000000000000 ,
b1111000111110000000000000000000 .
b10011 '
b10011 -
b1111110100101000111100011111 "
b1111110100101000111100011111 +
b10011 =
b1111110100101000111100011111 ;
b10011 &
b1111110100101000111100011111 $
b100000 (
b101000 )
b101000 *
b10100000000011111100000000000000 5
b10100000000011111100000000000000 :
b10100000000011111100000000000000 9
b11100000101000000000111111000000 8
b1111110000010100000000011111100 7
b1111110000010100000000011111100 6
#41000
b11100000101001000100001111000000 0
b11100000101001000100001111000000 1
b11000000000000000000000000000000 !
b11000000000000000000000000000000 ,
b11000000000000000000000000000000 .
b1111000001010010001000011110000 2
b10100100010000111100000000000000 /
b11011 '
b11011 -
b10111100000101001000100001111000 "
b10111100000101001000100001111000 +
b11011 =
b10111100000101001000100001111000 ;
b11011 &
b10111100000101001000100001111000 $
b100001 (
b101001 )
b101001 *
b1111000111110000000000000000000 5
b1111000111110000000000000000000 :
b1111110100101000111100011111000 9
b1111110100101000111100011111000 8
b1111110100101000111100011111000 7
b11111101001010001111000111110 6
#42000
b100111111111001010101110001111 0
b100111111111001010101110001111 1
b1001111111110010101011 /
b10011111111100101010111000111111 2
b1001111111110010101011 !
b1001111111110010101011 ,
b1001111111110010101011 .
0#
b1010 '
b1010 -
b10011111111100101010111000111111 "
b10011111111100101010111000111111 +
0<
b1010 =
b10011111111100101010111000111111 ;
0%
b1010 &
b10011111111100101010111000111111 $
b100010 (
b101010 )
b101010 *
b11000000000000000000000000000000 5
b11000000000000000000000000000000 :
b10100100010000111100000000000000 9
b11100000101001000100001111000000 8
b11100000101001000100001111000000 7
b1111000001010010001000011110000 6
