Module 2/Week 1/Sequence Detector/seqDetectorMoore.sv
module seqDetectorMoore(w, clk, z);
    input w, clk;
    output reg z;

    reg [1:0] state, next_state;

    initial begin
        state = 2'b00;
        next_state = 2'b00;
        z = 1'b0;
    end

    always @(state, w) begin
        case (state)
            2'b00: begin
                if (w == 1'b0)
                    next_state = 2'b00;
                else
                    next_state = 2'b01;
                z = 1'b0;
            end
            2'b01: begin
                if (w == 1'b0)
                    next_state = 2'b00;
                else
                    next_state = 2'b10;
                z = 1'b0;
            end
            2'b10: begin
                if (w == 1'b0)
                    next_state = 2'b00;
                else
                    next_state = 2'b10;
                z = 1'b1;
            end
            default: begin
                next_state = 2'b00;
                z = 1'b0;
            end
        endcase
    end

    always @(posedge clk) begin
        state <= next_state;
    end

endmodule

Module_2/Week_1/Sequence_Detector/seqDetectorMoore_tb.sv
`timescale 1ns / 1ps

module seqDetectorMoore_tb;

    reg  w;
    reg  clk;
    wire z;

    // Instantiate DUT
    seqDetectorMoore dut (
        .w   (w),
        .clk (clk),
        .z   (z)
    );

    // Test vector
    reg [11:0] stimulus = 12'b010110111000;
    integer i;

    // Printing waveform
    initial begin
        $dumpfile("seqDetectorMoore_tb.vcd");
        $dumpvars(0, seqDetectorMoore_tb);
    end

    // Clock generation: 10 ns period
    always #5 clk = ~clk;

    initial begin
        // Initial values
        clk = 0;
        w   = 0;

        $display("Time\tclk\tw\tz");
        $display("------------------------");

        // Apply stimulus bit-by-bit
        for (i = 11; i >= 0; i = i - 1) begin
            @(negedge clk);
            w = stimulus[i];
            @(posedge clk);
            $display("%0t\t%b\t%b\t%b", $time, clk, w, z);
        end

        #10;
        $finish;
    end

endmodule

Module_2/Week_1/Sequence_Detector/seqDetectorMoore_tb.vcd
$date
	Mon Dec 22 12:18:47 2025
$end
$version
	Icarus Verilog
$end
$timescale
	1ps
$end
$scope module seqDetectorMoore_tb $end
$var wire 1 ! z $end
$var reg 1 " clk $end
$var reg 12 # stimulus [11:0] $end
$var reg 1 $ w $end
$var integer 32 % i [31:0] $end
$scope module dut $end
$var wire 1 " clk $end
$var wire 1 $ w $end
$var reg 2 & next_state [1:0] $end
$var reg 2 ' state [1:0] $end
$var reg 1 ! z $end
$upscope $end
$upscope $end
$enddefinitions $end
$comment Show the parameter values. $end
$dumpall
$end
#0
$dumpvars
b0 '
b0 &
b1011 %
0$
b10110111000 #
0"
0!
$end
#5000
1"
#10000
0"
#15000
b1010 %
1"
#20000
b1 &
1$
0"
#25000
b10 &
b1 '
b1001 %
1"
#30000
b0 &
0$
0"
#35000
b0 '
b1000 %
1"
#40000
b1 &
1$
0"
#45000
b10 &
b1 '
b111 %
1"
#50000
0"
#55000
1!
b10 '
b110 %
1"
#60000
b0 &
0$
0"
#65000
0!
b0 '
b101 %
1"
#70000
b1 &
1$
0"
#75000
b10 &
b1 '
b100 %
1"
#80000
0"
#85000
1!
b10 '
b11 %
1"
#90000
0"
#95000
b10 %
1"
#100000
b0 &
0$
0"
#105000
0!
b0 '
b1 %
1"
#110000
0"
#115000
b0 %
1"
#120000
0"
#125000
b11111111111111111111111111111111 %
1"
