Module_2/Week_1/Tasks/Adder_32bit/adder32.sv
//------------------------------------------------------------------------------
// Module: 32_bit_CLA
// Description:
//   It is a 32-bit adder block that works on carry-lookahead principle. It is
//   implemented by cascading 4 8-bit carry-lookahead adders to cater for
//   32-bits.
//
// Author      : Muhammad Ahmed Qazi
// Date        : 2025-12-16
//------------------------------------------------------------------------------

module CLA_8bit #(
	
	// Parameter declarations
	parameter integer DATA_WIDTH = 8
	)(
	
	// Port declarations
	input   [DATA_WIDTH - 1:0] a, 
	input	[DATA_WIDTH - 1:0] b,
	input                      cin,

	output  [DATA_WIDTH - 1:0] sum,
	output                     cout
	);

	// Internal signals
	wire [DATA_WIDTH-1:0] G;
	wire [DATA_WIDTH-1:0] P;
	wire [DATA_WIDTH:0]   C;

	// Combinational logic
	
	// Bit-level generate and propagate
	assign G = a & b;
	assign P = a ^ b;

	// Initial carry
	assign C[0] = cin;

	// Carry-lookahead logic
	genvar i;
	generate
		for (i = 0; i < DATA_WIDTH; i = i + 1) begin : CLA_CARRY
			assign C[i + 1] = G[i] | (P[i] & C[i]);
		end
	endgenerate

	// Sum calculation
	assign sum = P ^ C[DATA_WIDTH-1:0];

	// Carry out calculation
	assign cout = C[DATA_WIDTH];

endmodule

module adder_32bit (
	
	// Port declarations
	input  [31:0] a,
	input  [31:0] b,
	input         cin,

	output [31:0] sum,
	output        cout
	);

	// Internal signals
	wire [31:0] adder_sum;
	wire [4:0]  adder_cout;

	assign adder_cout[0] = cin;
	
	// Module instantiation
	genvar i;
	generate
        for (i = 0; i < 4; i = i + 1) begin : CLA_BLOCKS
            CLA_8bit #(.DATA_WIDTH(8)) cla_inst (
                .a   (a[i*8 +: 8]),
                .b   (b[i*8 +: 8]),
                .cin (adder_cout[i]),
                .sum (adder_sum[i*8 +: 8]),
                .cout(adder_cout[i+1])
            );
        end
    endgenerate
	
	assign sum = adder_sum;
	assign cout = adder_cout[4];

endmodule

Module 2/Week 1/Tasks/Adder_32bit/adder32_tb.sv
`timescale 1ns/1ps

module adder32_tb;

    // Testbench signals
    reg  [31:0] a, b;
    reg         cin;
    wire [31:0] sum;
    wire        cout;

    // Instantiate DUT
    adder_32bit dut (
        .a   (a),
        .b   (b),
        .cin (cin),
        .sum (sum),
        .cout(cout)
    );

    // Counters
    integer total_tests = 0;
    integer passed_tests = 0;

    // Task to apply test and check result
    task check_adder;
        input [31:0] test_a, test_b;
        input        test_cin;
        reg   [31:0] expected_sum;
        reg          expected_cout;
        begin
            a = test_a;
            b = test_b;
            cin = test_cin;
            #1; // small delay for combinational logic to settle
            
            {expected_cout, expected_sum} = test_a + test_b + test_cin;
            
            total_tests = total_tests + 1;
            
            if (sum === expected_sum && cout === expected_cout) begin
                $display("TEST %0d PASS: a=%h b=%h cin=%b sum=%h cout=%b", 
                          total_tests, a, b, cin, sum, cout);
                passed_tests = passed_tests + 1;
            end else begin
                $display("TEST %0d FAIL: a=%h b=%h cin=%b sum=%h (expected %h) cout=%b (expected %b)", 
                          total_tests, a, b, cin, sum, expected_sum, cout, expected_cout);
            end
        end
    endtask

    // Printing waveform
	 initial begin
		 $dumpfile("adder_32.vcd");
		 $dumpvars(0, adder32_tb);
	 end

    // Test sequence
    integer i;
    initial begin
        $display("----- Starting 32-bit Adder Self-Checking Testbench -----");
        
        // ----- Directed tests -----
        check_adder(32'h0000_0000, 32'h0000_0000, 1'b0); // 0 + 0
        check_adder(32'hFFFF_FFFF, 32'hFFFF_FFFF, 1'b0); // max + max
        check_adder(32'h8000_0000, 32'h8000_0000, 1'b0); // overflow
        check_adder(32'h1234_5678, 32'h8765_4321, 1'b1); // mixed + carry

        // ----- Random tests -----
        for (i = 0; i < 50; i = i + 1) begin
            check_adder($random, $random, $random % 2);
        end

        // ----- Summary -----
        $display("----- Testbench Summary -----");
        $display("Total tests run : %0d", total_tests);
        $display("Tests passed    : %0d", passed_tests);
        $display("Tests failed    : %0d", total_tests - passed_tests);
        $finish;
    end

endmodule

Module_2/Week_1/Tasks/Adder_32bit/adder_32.vcd
$date
	Tue Dec 23 09:44:18 2025
$end
$version
	Icarus Verilog
$end
$timescale
	1ps
$end
$scope module adder32_tb $end
$var wire 32 ! sum [31:0] $end
$var wire 1 " cout $end
$var reg 32 # a [31:0] $end
$var reg 32 $ b [31:0] $end
$var reg 1 % cin $end
$var integer 32 & i [31:0] $end
$var integer 32 ' passed_tests [31:0] $end
$var integer 32 ( total_tests [31:0] $end
$scope module dut $end
$var wire 32 ) a [31:0] $end
$var wire 32 * b [31:0] $end
$var wire 1 % cin $end
$var wire 32 + sum [31:0] $end
$var wire 1 " cout $end
$var wire 32 , adder_sum [31:0] $end
$var wire 5 - adder_cout [4:0] $end
$scope begin CLA_BLOCKS[0] $end
$var parameter 2 . i $end
$scope module cla_inst $end
$var wire 8 / G [7:0] $end
$var wire 8 0 P [7:0] $end
$var wire 8 1 a [7:0] $end
$var wire 8 2 b [7:0] $end
$var wire 1 3 cin $end
$var wire 8 4 sum [7:0] $end
$var wire 1 5 cout $end
$var wire 9 6 C [8:0] $end
$var parameter 32 7 DATA_WIDTH $end
$scope begin CLA_CARRY[0] $end
$var parameter 2 8 i $end
$upscope $end
$scope begin CLA_CARRY[1] $end
$var parameter 2 9 i $end
$upscope $end
$scope begin CLA_CARRY[2] $end
$var parameter 3 : i $end
$upscope $end
$scope begin CLA_CARRY[3] $end
$var parameter 3 ; i $end
$upscope $end
$scope begin CLA_CARRY[4] $end
$var parameter 4 < i $end
$upscope $end
$scope begin CLA_CARRY[5] $end
$var parameter 4 = i $end
$upscope $end
$scope begin CLA_CARRY[6] $end
$var parameter 4 > i $end
$upscope $end
$scope begin CLA_CARRY[7] $end
$var parameter 4 ? i $end
$upscope $end
$upscope $end
$upscope $end
$scope begin CLA_BLOCKS[1] $end
$var parameter 2 @ i $end
$scope module cla_inst $end
$var wire 8 A G [7:0] $end
$var wire 8 B P [7:0] $end
$var wire 8 C a [7:0] $end
$var wire 8 D b [7:0] $end
$var wire 1 E cin $end
$var wire 8 F sum [7:0] $end
$var wire 1 G cout $end
$var wire 9 H C [8:0] $end
$var parameter 32 I DATA_WIDTH $end
$scope begin CLA_CARRY[0] $end
$var parameter 2 J i $end
$upscope $end
$scope begin CLA_CARRY[1] $end
$var parameter 2 K i $end
$upscope $end
$scope begin CLA_CARRY[2] $end
$var parameter 3 L i $end
$upscope $end
$scope begin CLA_CARRY[3] $end
$var parameter 3 M i $end
$upscope $end
$scope begin CLA_CARRY[4] $end
$var parameter 4 N i $end
$upscope $end
$scope begin CLA_CARRY[5] $end
$var parameter 4 O i $end
$upscope $end
$scope begin CLA_CARRY[6] $end
$var parameter 4 P i $end
$upscope $end
$scope begin CLA_CARRY[7] $end
$var parameter 4 Q i $end
$upscope $end
$upscope $end
$upscope $end
$scope begin CLA_BLOCKS[2] $end
$var parameter 3 R i $end
$scope module cla_inst $end
$var wire 8 S G [7:0] $end
$var wire 8 T P [7:0] $end
$var wire 8 U a [7:0] $end
$var wire 8 V b [7:0] $end
$var wire 1 W cin $end
$var wire 8 X sum [7:0] $end
$var wire 1 Y cout $end
$var wire 9 Z C [8:0] $end
$var parameter 32 [ DATA_WIDTH $end
$scope begin CLA_CARRY[0] $end
$var parameter 2 \ i $end
$upscope $end
$scope begin CLA_CARRY[1] $end
$var parameter 2 ] i $end
$upscope $end
$scope begin CLA_CARRY[2] $end
$var parameter 3 ^ i $end
$upscope $end
$scope begin CLA_CARRY[3] $end
$var parameter 3 _ i $end
$upscope $end
$scope begin CLA_CARRY[4] $end
$var parameter 4 ` i $end
$upscope $end
$scope begin CLA_CARRY[5] $end
$var parameter 4 a i $end
$upscope $end
$scope begin CLA_CARRY[6] $end
$var parameter 4 b i $end
$upscope $end
$scope begin CLA_CARRY[7] $end
$var parameter 4 c i $end
$upscope $end
$upscope $end
$upscope $end
$scope begin CLA_BLOCKS[3] $end
$var parameter 3 d i $end
$scope module cla_inst $end
$var wire 8 e G [7:0] $end
$var wire 8 f P [7:0] $end
$var wire 8 g a [7:0] $end
$var wire 8 h b [7:0] $end
$var wire 1 i cin $end
$var wire 8 j sum [7:0] $end
$var wire 1 k cout $end
$var wire 9 l C [8:0] $end
$var parameter 32 m DATA_WIDTH $end
$scope begin CLA_CARRY[0] $end
$var parameter 2 n i $end
$upscope $end
$scope begin CLA_CARRY[1] $end
$var parameter 2 o i $end
$upscope $end
$scope begin CLA_CARRY[2] $end
$var parameter 3 p i $end
$upscope $end
$scope begin CLA_CARRY[3] $end
$var parameter 3 q i $end
$upscope $end
$scope begin CLA_CARRY[4] $end
$var parameter 4 r i $end
$upscope $end
$scope begin CLA_CARRY[5] $end
$var parameter 4 s i $end
$upscope $end
$scope begin CLA_CARRY[6] $end
$var parameter 4 t i $end
$upscope $end
$scope begin CLA_CARRY[7] $end
$var parameter 4 u i $end
$upscope $end
$upscope $end
$upscope $end
$upscope $end
$scope task check_adder $end
$var reg 1 v expected_cout $end
$var reg 32 w expected_sum [31:0] $end
$var reg 32 x test_a [31:0] $end
$var reg 32 y test_b [31:0] $end
$var reg 1 z test_cin $end
$upscope $end
$upscope $end
$enddefinitions $end
$comment Show the parameter values. $end
$dumpall
b111 u
b110 t
b101 s
b100 r
b11 q
b10 p
b1 o
b0 n
b1000 m
b11 d
b111 c
b110 b
b101 a
b100 `
b11 _
b10 ^
b1 ]
b0 \
b1000 [
b10 R
b111 Q
b110 P
b101 O
b100 N
b11 M
b10 L
b1 K
b0 J
b1000 I
b1 @
b111 ?
b110 >
b101 =
b100 <
b11 ;
b10 :
b1 9
b0 8
b1000 7
b0 .
$end
#0
$dumpvars
0z
b0 y
b0 x
bx w
xv
b0 l
0k
b0 j
0i
b0 h
b0 g
b0 f
b0 e
b0 Z
0Y
b0 X
0W
b0 V
b0 U
b0 T
b0 S
b0 H
0G
b0 F
0E
b0 D
b0 C
b0 B
b0 A
b0 6
05
b0 4
03
b0 2
b0 1
b0 0
b0 /
b0 -
b0 ,
b0 +
b0 *
b0 )
b0 (
b0 '
bx &
0%
b0 $
b0 #
0"
b0 !
$end
#1000
b11111110 4
1E
b11111111 F
1W
b11111111 X
1i
b11111111111111111111111111111110 !
b11111111111111111111111111111110 +
b11111111111111111111111111111110 ,
b11111111 j
1"
15
1G
1Y
b11110 -
1k
b111111110 6
b111111111 H
b111111111 Z
b111111111 l
b11111111 /
b11111111 A
b11111111 S
b11111111 e
b11111111 2
b11111111 D
b11111111 V
b11111111 h
b11111111 1
b11111111 C
b11111111 U
b11111111 g
b11111111111111111111111111111111 $
b11111111111111111111111111111111 *
b11111111111111111111111111111111 #
b11111111111111111111111111111111 )
b11111111111111111111111111111111 y
b11111111111111111111111111111111 x
b1 '
b1 (
0v
b0 w
#2000
b0 4
0E
b0 F
0W
b0 X
0i
b0 !
b0 +
b0 ,
b0 j
05
0G
b10000 -
0Y
b0 6
b0 H
b0 Z
b100000000 l
b0 /
b0 A
b0 S
b10000000 e
b0 2
b0 D
b0 V
b10000000 h
b0 1
b0 C
b0 U
b10000000 g
b10000000000000000000000000000000 $
b10000000000000000000000000000000 *
b10000000000000000000000000000000 #
b10000000000000000000000000000000 )
b10000000000000000000000000000000 y
b10000000000000000000000000000000 x
b10 '
b10 (
1v
b11111111111111111111111111111110 w
#3000
0"
0k
b10001100 H
b11001000 Z
b1100 l
b10011010 4
b10011001 F
b10011001 X
b10011001100110011001100110011010 !
b10011001100110011001100110011010 +
b10011001100110011001100110011010 ,
b10011001 j
b100000 /
b1011001 0
b1000010 A
b10101 B
b100100 S
b1010001 T
b10 e
b10010101 f
b11000011 6
13
b100001 2
b1000011 D
b1100101 V
b10000111 h
b1111000 1
b1010110 C
b110100 U
b10010 g
b1 -
1%
b10000111011001010100001100100001 $
b10000111011001010100001100100001 *
b10010001101000101011001111000 #
b10010001101000101011001111000 )
1z
b10000111011001010100001100100001 y
b10010001101000101011001111000 x
b11 '
b11 (
b0 w
#4000
0E
0i
05
b1 -
0Y
b0 l
b11 6
b11111000 H
b10 Z
b11010010 j
b10100110 4
b10010011 F
b11010010100111101001001110100110 !
b11010010100111101001001110100110 +
b11010010100111101001001110100110 ,
b10011110 X
b0 e
b11010010 f
b0 /
b10100101 0
b10100 A
b1101011 B
b1 S
b10011100 T
b10000001 2
b1011110 D
b10001001 V
b11000000 h
b100100 1
b110101 C
b10101 U
b11000000100010010101111010000001 $
b11000000100010010101111010000001 *
b10010000101010011010100100100 #
b10010000101010011010100100100 )
b11000000100010010101111010000001 y
b10010000101010011010100100100 x
b0 &
b100 '
b100 (
0v
b10011001100110011001100110011010 w
#5000
b1111 l
1i
b11111 6
b1001 -
1Y
b11111100 H
b111100000 Z
b1110001 4
b11010001 F
b10101001 X
b10111000101010011101000101110001 !
b10111000101010011101000101110001 +
b10111000101010011101000101110001 ,
b10111000 j
b1 /
b1101110 0
b1010010 A
b101101 B
b10110000 S
b1001001 T
b10110111 f
b1101 2
b1111011 D
b10111001 V
b110 h
b1100011 1
b1010110 C
b11110000 U
b10110001 g
b110101110010111101100001101 $
b110101110010111101100001101 *
b10110001111100000101011001100011 #
b10110001111100000101011001100011 )
b110101110010111101100001101 y
b10110001111100000101011001100011 x
b1 &
b101 '
b101 (
b11010010100111101001001110100110 w
#6000
0i
0Y
0W
0G
1"
b1111 6
b10001 -
1k
b0 H
b1100 Z
b100000000 l
b1111000 4
b11010110 F
b11111001 X
b111011111110011101011001111000 !
b111011111110011101011001111000 +
b111011111110011101011001111000 ,
b111011 j
b0 /
b1110111 0
b0 A
b11010110 B
b10 S
b11110101 T
b10000000 e
b111011 f
b10010 2
b1010010 D
b110111 V
b10001001 h
b1100101 1
b10000100 C
b11000010 U
b10110010 g
b10001001001101110101001000010010 $
b10001001001101110101001000010010 *
b10110010110000101000010001100101 #
b10110010110000101000010001100101 )
b10001001001101110101001000010010 y
b10110010110000101000010001100101 x
b10 &
b110 '
b110 (
b10111000101010011101000101110001 w
#7000
1W
0"
b11111111 6
1G
b101 -
0k
b110000010 H
b1111 Z
b1111100 l
b10000100 4
b10111110 F
b11111011 X
b1000001111110111011111010000100 !
b1000001111110111011111010000100 +
b1000001111110111011111010000100 ,
b1000001 j
b100 /
b1111011 0
b11000001 A
b111100 B
b11 S
b11110100 T
b10 e
b111101 f
b1110110 2
b11110001 D
b100011 V
b111011 h
b1101 1
b11001101 C
b11010111 U
b110 g
b111011001000111111000101110110 $
b111011001000111111000101110110 *
b110110101111100110100001101 #
b110110101111100110100001101 )
b111011001000111111000101110110 y
b110110101111100110100001101 x
b11 &
b111 '
b111 (
1v
b111011111110011101011001111000 w
#8000
1i
1Y
1E
b1111 -
15
b100011011 6
b111101111 H
b111111011 Z
b10001101 l
b1111010 4
b1001111 F
b10 X
b10111101000000100100111101111010 !
b10111101000000100100111101111010 +
b10111101000000100100111101111010 ,
b10111101 j
b10001100 /
b1100001 0
b1010111 A
b10100000 B
b100 S
b11111001 T
b1000110 e
b110000 f
b10001100 2
b11110111 D
b101101 V
b1000110 h
b11101101 1
b1010111 C
b11010100 U
b1110110 g
b1000110001011011111011110001100 $
b1000110001011011111011110001100 *
b1110110110101000101011111101101 #
b1110110110101000101011111101101 )
b1000110001011011111011110001100 y
b1110110110101000101011111101101 x
b100 &
b1000 '
b1000 (
0v
b1000001111110111011111010000100 w
#9000
0W
0G
b10101001 F
1"
1k
b1001 H
b111101110 Z
b111000111 l
b10001011 4
b101110 X
b11000110001011101010100110001011 !
b11000110001011101010100110001011 +
b11000110001011101010100110001011 ,
b11000110 j
b11000100 /
b11 0
b100 A
b110111 S
b11000000 T
b11100010 e
b1 f
b110001000 6
03
b11000101 2
b10000100 D
b11110111 V
b11100010 h
b11000110 1
b100100 C
b110111 U
b11100011 g
b11010 -
0%
b11100010111101111000010011000101 $
b11100010111101111000010011000101 *
b11100011001101110010010011000110 #
b11100011001101110010010011000110 )
0z
b11100010111101111000010011000101 y
b11100011001101110010010011000110 x
b101 &
b1001 '
b1001 (
b10111101000000100100111101111010 w
#10000
1W
b11110 -
1G
b111001110 6
b111101111 H
b111111111 Z
b111100111 l
b1011100 4
b1101010 F
b10000010 X
b101110100000100110101001011100 !
b101110100000100110101001011100 +
b101110100000100110101001011100 ,
b101110 j
b1100101 /
b10010010 0
b1110010 A
b10000101 B
b10000010 S
b1111101 T
b110010 e
b11001001 f
b1110111 2
b1110010 D
b11010010 V
b10111011 h
b11100101 1
b11110111 C
b10101111 U
b1110010 g
b10111011110100100111001001110111 $
b10111011110100100111001001110111 *
b1110010101011111111011111100101 #
b1110010101011111111011111100101 )
b10111011110100100111001001110111 y
b1110010101011111111011111100101 x
b110 &
b1010 '
b1010 (
1v
b11000110001011101010100110001011 w
#11000
0"
b1110 -
0k
b111111100 6
b111110111 H
b111000001 Z
b11111111 l
b10000001 4
b1000101 F
b11101 X
b11000001000111010100010110000001 !
b11000001000111010100010110000001 +
b11000001000111010100010110000001 ,
b11000001 j
b10000010 /
b1111101 0
b1001001 A
b10110010 B
b100000 S
b11011100 T
b1000001 e
b111110 f
b11110010 2
b1101001 D
b110000 V
b1111001 h
b10001111 1
b11011011 C
b11101100 U
b1000111 g
b1111001001100000110100111110010 $
b1111001001100000110100111110010 *
b1000111111011001101101110001111 #
b1000111111011001101101110001111 )
b1111001001100000110100111110010 y
b1000111111011001101101110001111 x
b111 &
b1011 '
b1011 (
b101110100000100110101001011100 w
#12000
0i
0Y
0W
0G
1"
b10010 -
1k
b110000000 6
b11111101 H
b0 Z
b111000000 l
b10101101 4
b11001001 F
b11001010 X
b11010110110010101100100110101101 !
b11010110110010101100100110101101 +
b11010110110010101100100110101101 ,
b11010110 j
b11000000 /
b101101 0
b1001010 A
b110100 B
b0 S
b11001010 T
b11100000 e
b10110 f
b11000101 2
b1001110 D
b11001010 V
b11100010 h
b11101000 1
b1111010 C
b0 U
b11110100 g
b11100010110010100100111011000101 $
b11100010110010100100111011000101 *
b11110100000000000111101011101000 #
b11110100000000000111101011101000 )
b11100010110010100100111011000101 y
b11110100000000000111101011101000 x
b1000 &
b1100 '
b1100 (
0v
b11000001000111010100010110000001 w
#13000
0E
05
1i
1Y
b11110000 H
b100011100 Z
b100111101 l
b11101011 4
b10000000 F
b111001 X
b1110101001110011000000011101011 !
b1110101001110011000000011101011 +
b1110101001110011000000011101011 ,
b1110101 j
b101101 /
b10010000 0
b1000 A
b1110000 B
b10001010 S
b100101 T
b10010110 e
b1001000 f
b1111011 6
13
b101101 2
b1011000 D
b10101011 V
b10010110 h
b10111101 1
b101000 C
b10001110 U
b11011110 g
b11001 -
1%
b10010110101010110101100000101101 $
b10010110101010110101100000101101 *
b11011110100011100010100010111101 #
b11011110100011100010100010111101 )
1z
b10010110101010110101100000101101 y
b11011110100011100010100010111101 x
b1001 &
b1101 '
b1101 (
1v
b11010110110010101100100110101101 w
#14000
0W
0G
1i
0"
1Y
0k
b1100 H
b111111110 Z
b11 l
b1101101 4
b11101001 F
b1100010 X
b10110111011000101110100101101101 !
b10110111011000101110100101101101 +
b10110111011000101110100101101101 ,
b10110111 j
b10 /
b1101001 0
b10 A
b11100101 B
b1100011 S
b10011100 T
b1 e
b10110100 f
b100 6
03
b1010 2
b10000111 D
b1110011 V
b101 h
b1100011 1
b1100010 C
b11101111 U
b10110001 g
b1000 -
0%
b101011100111000011100001010 $
b101011100111000011100001010 *
b10110001111011110110001001100011 #
b10110001111011110110001001100011 )
0z
b101011100111000011100001010 y
b10110001111011110110001001100011 x
b1010 &
b1110 '
b1110 (
b1110101001110011000000011101011 w
#15000
0i
0Y
b10 H
b11000000 Z
b100000 l
b11001011 4
b1100110 F
b11011100 X
b1100101110111000110011011001011 !
b1100101110111000110011011001011 +
b1100101110111000110011011001011 ,
b1100101 j
b100000 /
b10001010 0
b1 A
b1100100 B
b1100000 S
b11100 T
b10000 e
b1000101 f
b1000001 6
13
b10101010 2
b1000101 D
b1111000 V
b1010101 h
b100000 1
b100001 C
b1100100 U
b10000 g
b1 -
1%
b1010101011110000100010110101010 $
b1010101011110000100010110101010 *
b10000011001000010000100100000 #
b10000011001000010000100100000 )
1z
b1010101011110000100010110101010 y
b10000011001000010000100100000 x
b1011 &
b1111 '
b1111 (
0v
b10110111011000101110100101101101 w
#16000
0i
0Y
1"
b10001 -
1k
b101111 6
b1110000 H
b0 Z
b100010110 l
b10101010 4
b11110110 F
b10100011 X
b1010100101000111111011010101010 !
b1010100101000111111011010101010 +
b1010100101000111111011010101010 ,
b1010100 j
b10010 /
b10000101 0
b111000 A
b10000110 B
b0 S
b10100011 T
b10001001 e
b1000010 f
b10011 2
b10111000 D
b10000011 V
b10001001 h
b10010110 1
b111110 C
b100000 U
b11001011 g
b10001001100000111011100000010011 $
b10001001100000111011100000010011 *
b11001011001000000011111010010110 #
b11001011001000000011111010010110 )
b10001001100000111011100000010011 y
b11001011001000000011111010010110 x
b1100 &
b10000 '
b10000 (
b1100101110111000110011011001011 w
#17000
1W
1i
0"
1G
1Y
b1101 -
0k
b10000111 6
b110111000 H
b101111111 Z
b1000011 l
b10111111 4
b10110011 F
b1000111 X
b11011111010001111011001110111111 !
b11011111010001111011001110111111 +
b11011111010001111011001110111111 ,
b11011111 j
b1000011 /
b111000 0
b11010100 A
b1011 B
b10000111 S
b111000 T
b100001 e
b10011100 f
b1101011 2
b11011101 D
b10011111 V
b110101 h
b1010011 1
b11010110 C
b10100111 U
b10101001 g
b110101100111111101110101101011 $
b110101100111111101110101101011 *
b10101001101001111101011001010011 #
b10101001101001111101011001010011 )
b110101100111111101110101101011 y
b10101001101001111101011001010011 x
b1101 &
b10001 '
b10001 (
1v
b1010100101000111111011010101010 w
#18000
0E
05
0W
0i
1"
0G
0Y
b10001 -
1k
b11101 6
b11111100 H
b101100 Z
b100001110 l
b10110001 4
b10001000 F
b1101101 X
b1011000011011011000100010110001 !
b1011000011011011000100010110001 +
b1011000011011011000100010110001 ,
b1011000 j
b10 /
b10101100 0
b1010 A
b1110100 B
b10110 S
b1000001 T
b10000001 e
b1010110 f
b10101110 2
b111110 D
b1010110 V
b11010111 h
b10 1
b1001010 C
b10111 U
b10000001 g
b11010111010101100011111010101110 $
b11010111010101100011111010101110 *
b10000001000101110100101000000010 #
b10000001000101110100101000000010 )
b11010111010101100011111010101110 y
b10000001000101110100101000000010 x
b1110 &
b10010 '
b10010 (
0v
b11011111010001111011001110111111 w
#19000
b1001001 X
1i
0"
1Y
0k
b10000000 H
b100001000 Z
b1111 l
b11110010 4
b10111011 F
b11111001010010011011101111110010 !
b11111001010010011011101111110010 +
b11111001010010011011101111110010 ,
b11111001 j
b11 /
b11101100 0
b1000000 A
b111011 B
b10000100 S
b1 e
b11110110 f
b11110 6
03
b100011 2
b1001001 D
b10000100 V
b10001 h
b11001111 1
b1110010 C
b11000101 U
b11100111 g
b1000 -
0%
b10001100001000100100100100011 $
b10001100001000100100100100011 *
b11100111110001010111001011001111 #
b11100111110001010111001011001111 )
0z
b10001100001000100100100100011 y
b11100111110001010111001011001111 x
b1111 &
b10011 '
b10011 (
1v
b1011000011011011000100010110001 w
#20000
1E
15
0i
1"
0Y
b10010 -
1k
b111110000 6
b10001 H
b11100110 Z
b111111000 l
b110 4
b1010111 F
b10100100 X
b10000011101001000101011100000110 !
b10000011101001000101011100000110 +
b10000011101001000101011100000110 ,
b10000011 j
b1000 /
b11110110 0
b1000 A
b1000110 B
b110001 S
b1000010 T
b10000100 e
b1111011 f
b111100 2
b1001100 D
b110001 V
b10011110 h
b11001010 1
b1010 C
b1110011 U
b11100101 g
b10011110001100010100110000111100 $
b10011110001100010100110000111100 *
b11100101011100110000101011001010 #
b11100101011100110000101011001010 )
b10011110001100010100110000111100 y
b11100101011100110000101011001010 x
b10000 &
b10100 '
b10100 (
0v
b11111001010010011011101111110010 w
#21000
0E
05
1W
1G
0i
0Y
0"
b100 -
0k
b0 6
b111000110 H
b11001 Z
b0 l
b11001011 4
b10100 F
b11110011 X
b1100101111100110001010011001011 !
b1100101111100110001010011001011 +
b1100101111100110001010011001011 ,
b1100101 j
b0 /
b11001011 0
b100001 A
b11010010 B
b100 S
b11101010 T
b0 e
b1100101 f
b1000001 2
b10110011 D
b11000100 V
b100000 h
b10001010 1
b1100001 C
b101110 U
b1000101 g
b100000110001001011001101000001 $
b100000110001001011001101000001 *
b1000101001011100110000110001010 #
b1000101001011100110000110001010 )
b100000110001001011001101000001 y
b1000101001011100110000110001010 x
b10001 &
b10101 '
b10101 (
1v
b10000011101001000101011100000110 w
#22000
1"
1k
1E
15
1W
1G
b111100111 H
b1 Z
b111111000 l
b10 4
b110 F
b10101011 X
b101010110000011000000010 !
b101010110000011000000010 +
b101010110000011000000010 ,
b0 j
b1000 /
b11110001 0
b10010 A
b11100001 B
b0 S
b10101010 T
b100 e
b11111000 f
b111110011 6
13
b10001001 2
b10010 D
b10001010 V
b11000100 h
b1111000 1
b11110011 C
b100000 U
b111100 g
b10111 -
1%
b11000100100010100001001010001001 $
b11000100100010100001001010001001 *
b111100001000001111001101111000 #
b111100001000001111001101111000 )
1z
b11000100100010100001001010001001 y
b111100001000001111001101111000 x
b10010 &
b10110 '
b10110 (
0v
b1100101111100110001010011001011 w
#23000
0"
0k
b111000011 H
b111 Z
b10000110 l
b1111100 4
b1011111 F
b1001110 X
b10111110010011100101111101111100 !
b10111110010011100101111101111100 +
b10111110010011100101111101111100 ,
b10111110 j
b10000110 /
b1110000 0
b1100001 A
b10011100 B
b10 S
b1001001 T
b1000011 e
b111000 f
b100001100 6
03
b11000110 2
b11111001 D
b1001011 V
b1100011 h
b10110110 1
b1100101 C
b10 U
b1011011 g
b110 -
0%
b1100011010010111111100111000110 $
b1100011010010111111100111000110 *
b1011011000000100110010110110110 #
b1011011000000100110010110110110 )
0z
b1100011010010111111100111000110 y
b1011011000000100110010110110110 x
b10011 &
b10111 '
b10111 (
1v
b101010110000011000000010 w
#24000
0W
0G
0"
0E
0k
05
b0 H
b11111110 Z
b111000 l
b11100111 4
b11011111 F
b10000100 X
b11110011100001001101111111100111 !
b11110011100001001101111111100111 +
b11110011100001001101111111100111 ,
b11110011 j
b101000 /
b10010110 0
b0 A
b11011111 B
b101 S
b1111010 T
b10100 e
b11001011 f
b1110001 6
13
b101010 2
b11011101 D
b1111 V
b10101 h
b10111100 1
b10 C
b1110101 U
b11011110 g
b1 -
1%
b10101000011111101110100101010 $
b10101000011111101110100101010 *
b11011110011101010000001010111100 #
b11011110011101010000001010111100 )
1z
b10101000011111101110100101010 y
b11011110011101010000001010111100 x
b10100 &
b11000 '
b11000 (
0v
b10111110010011100101111101111100 w
#25000
0W
0G
0"
0k
b0 H
0E
05
1i
b1001 -
1Y
b11 6
b111101100 Z
b1 l
b11110111 4
b11111111 F
b10001001 X
b11111011100010011111111111110111 !
b11111011100010011111111111110111 +
b11111011100010011111111111110111 ,
b11111011 j
b1 /
b11110100 0
b11111111 B
b10010010 S
b1100101 T
b0 e
b11111010 f
b10000101 2
b1000001 D
b11110010 V
b1000010 h
b1110001 1
b10111110 C
b10010111 U
b10111000 g
b1000010111100100100000110000101 $
b1000010111100100100000110000101 *
b10111000100101111011111001110001 #
b10111000100101111011111001110001 )
b1000010111100100100000110000101 y
b10111000100101111011111001110001 x
b10101 &
b11001 '
b11001 (
b11110011100001001101111111100111 w
#26000
0i
0Y
b11000000 H
b11000 Z
b111010 l
b1110101 4
b10010011 F
b11010010 X
b10111010110100101001001101110101 !
b10111010110100101001001101110101 +
b10111010110100101001001101110101 ,
b10111010 j
b111010 /
b1 0
b100000 A
b1010011 B
b100 S
b11001010 T
b11101 e
b10000000 f
b1110100 6
03
b111010 2
b110011 D
b110 V
b11101 h
b111011 1
b1100000 C
b11001100 U
b10011101 g
b0 -
0%
b11101000001100011001100111010 $
b11101000001100011001100111010 *
b10011101110011000110000000111011 #
b10011101110011000110000000111011 )
0z
b11101000001100011001100111010 y
b10011101110011000110000000111011 x
b10110 &
b11010 '
b11010 (
b11111011100010011111111111110111 w
#27000
1E
15
0W
0G
1i
1Y
b110111 H
b111110000 Z
b11110001 l
b111 4
b11100111 F
b10000011 X
b10000011100000111110011100000111 !
b10000011100000111110011100000111 +
b10000011100000111110011100000111 ,
b10000011 j
b10001 /
b11100100 0
b1011 A
b11010000 B
b10001000 S
b1110011 T
b1000 e
b1110010 f
b111100011 6
13
b11110001 2
b10011011 D
b11011001 V
b1111000 h
b10101 1
b1001011 C
b10101010 U
b1010 g
b1011 -
1%
b1111000110110011001101111110001 $
b1111000110110011001101111110001 *
b1010101010100100101100010101 #
b1010101010100100101100010101 )
1z
b1111000110110011001101111110001 y
b1010101010100100101100010101 x
b10111 &
b11011 '
b11011 (
b10111010110100101001001101110101 w
#28000
1W
1G
0E
05
0i
b101 -
0Y
b10000001 6
b111111110 H
b1001111 Z
b1000000 l
b10101111 4
b10 F
b1011001 X
b1010111010110010000001010101111 !
b1010111010110010000001010101111 +
b1010111010110010000001010101111 ,
b1010111 j
b1000000 /
b101110 0
b11 A
b11111100 B
b100001 S
b10110 T
b100000 e
b10111 f
b1001100 2
b11111011 D
b110101 V
b100110 h
b1100010 1
b111 C
b100011 U
b110001 g
b100110001101011111101101001100 $
b100110001101011111101101001100 *
b110001001000110000011101100010 #
b110001001000110000011101100010 )
b100110001101011111101101001100 y
b110001001000110000011101100010 x
b11000 &
b11100 '
b11100 (
b10000011100000111110011100000111 w
