Module_2/Week_1/Tasks/Encoder_8to3/encoder.sv
//------------------------------------------------------------------------------
// Module: encoder_8to3
// Description:
//   Priority encoder with 8 inputs and 3 outputs. Works on high priority
//   concept, i.e., if multiple inputs are active, output would be according
//   to the most significant input.
//
// Author      : Muhammad Ahmed Qazi
// Date        : 2025-12-18
//------------------------------------------------------------------------------

module encoder #(

	// Parameter declarations
	parameter integer INP_WIDTH = 8,
		parameter integer OUP_WIDTH = 3
		)(

			// Port declarations
			input  [INP_WIDTH - 1: 0] in,
			input                     en,

			output [OUP_WIDTH - 1: 0] out,
			output                    gs,
			output                    e0
			);

			// Internal signals
			reg [OUP_WIDTH - 1: 0] reg_out;
			reg                   reg_gs;
			reg                   reg_e0;

			// Functionality
			always @(*) begin

				// Default assignments
				reg_out = {OUP_WIDTH{1'b0}};
				reg_gs = 1'b0;
				reg_e0 = 1'b0;

				if (en) begin
				if      (in[7]) begin
					reg_out  = 3'b111;
					reg_gs  = 1'b1;
				end
				else if (in[6]) begin
					reg_out  = 3'b110;
					reg_gs  = 1'b1;
				end
				else if (in[5]) begin
					reg_out  = 3'b101;
					reg_gs  = 1'b1;
				end
				else if (in[4]) begin
					reg_out  = 3'b100;
					reg_gs  = 1'b1;
				end
				else if (in[3]) begin
					reg_out  = 3'b011;
					reg_gs  = 1'b1;
				end
				else if (in[2]) begin
					reg_out  = 3'b010;
					reg_gs  = 1'b1;
				end
				else if (in[1]) begin
					reg_out  = 3'b001;
					reg_gs  = 1'b1;
				end
				else if (in[0]) begin
					reg_out  = 3'b000;
					reg_gs  = 1'b1;
				end
				else            begin
					reg_out  = 3'b000;
					reg_e0  = 1'b1;
				end
			end
		end

		assign out = reg_out;
		assign gs = reg_gs;
		assign e0 = reg_e0;

endmodule

Module 2/Week 1/Tasks/Encoder_8to3/encoder_tb.sv
`timescale 1ns/1ps

module encoder_tb;

    // Testbench signals
    reg  [7:0] in;
    reg        en;
    wire [2:0] out;
    wire       gs, e0;

    // Instantiate DUT
    encoder dut (
        .in  (in),
        .en  (en),
        .out (out),
        .gs  (gs),
        .e0  (e0)
    );

    // Counters
    integer total_tests = 0;
    integer passed_tests = 0;

    // Task to compute expected outputs and check DUT
    task check_encoder;
        input [7:0] test_in;
        input       test_en;
        reg [2:0] expected_out;
        reg expected_gs;
        reg expected_e0;
        integer i;
        reg found;
        begin
            in = test_in;
            en = test_en;
            #1; // small delay for combinational logic

            // Default values
            expected_out = 3'b000;
            expected_gs  = 1'b0;
            expected_e0  = 1'b0;

            found = 0;
            if (test_en) begin
                for (i = 7; i >= 0; i = i - 1) begin
                    if (test_in[i] && !found) begin
                        expected_out = i[2:0];
                        expected_gs  = 1'b1;
                        expected_e0  = 1'b0;
                        found = 1; // stop further updates
                    end
                end
                if (!found) begin
                    // no bits set
                    expected_out = 3'b000;
                    expected_gs  = 1'b0;
                    expected_e0  = 1'b1;
                end
            end else begin
                // encoder disabled
                expected_out = 3'b000;
                expected_gs  = 1'b0;
                expected_e0  = 1'b0;
            end

            // Check DUT outputs
            total_tests = total_tests + 1;
            if (out === expected_out && gs === expected_gs && e0 === expected_e0) begin
                $display("TEST %0d PASS: in=%b en=%b out=%b gs=%b e0=%b", 
                          total_tests, in, en, out, gs, e0);
                passed_tests = passed_tests + 1;
            end else begin
                $display("TEST %0d FAIL: in=%b en=%b out=%b (expected %b) gs=%b (expected %b) e0=%b (expected %b)", 
                          total_tests, in, en, out, expected_out, gs, expected_gs, e0, expected_e0);
            end
        end
    endtask

    // Printing waveform
    initial begin
        $dumpfile("encoder_8to3.vcd");
        $dumpvars(0, encoder_tb);
    end

    // Test sequence
    integer i;
    initial begin
        $display("----- Starting 8-to-3 Encoder Self-Checking Testbench -----");

        // ----- Directed tests: single high bit -----
        for (i = 0; i < 8; i = i + 1) begin
            check_encoder(8'b1 << i, 1'b1);
        end

        // ----- Directed test: all zeros -----
        check_encoder(8'b0000_0000, 1'b1);

        // ----- Directed test: disabled -----
        check_encoder(8'b1111_1111, 1'b0);

        // ----- Random tests: multiple bits high -----
        for (i = 0; i < 20; i = i + 1) begin
            check_encoder($random % 256, 1'b1);
        end

        // ----- Summary -----
        $display("----- Testbench Summary -----");
        $display("Total tests run : %0d", total_tests);
        $display("Tests passed    : %0d", passed_tests);
        $display("Tests failed    : %0d", total_tests - passed_tests);
        $finish;
    end

endmodule

Module 2/Week 1/Tasks/Encoder_8to3/encoder_8to3.vcd
$date
	Thu Dec 18 14:49:55 2025
$end
$version
	Icarus Verilog
$end
$timescale
	1ps
$end
$scope module encoder_tb $end
$var wire 3 ! out [2:0] $end
$var wire 1 " gs $end
$var wire 1 # e0 $end
$var reg 1 $ en $end
$var reg 8 % in [7:0] $end
$var integer 32 & i [31:0] $end
$var integer 32 ' passed_tests [31:0] $end
$var integer 32 ( total_tests [31:0] $end
$scope module dut $end
$var wire 1 # e0 $end
$var wire 1 $ en $end
$var wire 1 " gs $end
$var wire 8 ) in [7:0] $end
$var wire 3 * out [2:0] $end
$var parameter 32 + INP_WIDTH $end
$var parameter 32 , OUP_WIDTH $end
$var reg 1 - reg_e0 $end
$var reg 1 . reg_gs $end
$var reg 3 / reg_out [2:0] $end
$upscope $end
$scope task check_encoder $end
$var reg 1 0 expected_e0 $end
$var reg 1 1 expected_gs $end
$var reg 3 2 expected_out [2:0] $end
$var reg 1 3 found $end
$var reg 1 4 test_en $end
$var reg 8 5 test_in [7:0] $end
$var integer 32 6 i [31:0] $end
$upscope $end
$upscope $end
$enddefinitions $end
$comment Show the parameter values. $end
$dumpall
b11 ,
b1000 +
$end
#0
$dumpvars
bx 6
b1 5
14
x3
bx 2
x1
x0
b0 /
1.
0-
b0 *
b1 )
b0 (
b0 '
b0 &
b1 %
1$
0#
1"
b0 !
$end
#1000
b1 !
b1 *
b1 /
1"
1.
b10 %
b10 )
b10 5
b1 &
b1 '
b1 (
b11111111111111111111111111111111 6
13
00
11
b0 2
#2000
1"
1.
b10 !
b10 *
b10 /
b100 %
b100 )
b100 5
b10 &
b10 '
b10 (
b1 2
b11111111111111111111111111111111 6
13
11
#3000
1"
1.
b11 !
b11 *
b11 /
b1000 %
b1000 )
b1000 5
b11 &
b11 '
b11 (
b11111111111111111111111111111111 6
13
11
b10 2
#4000
1"
1.
b100 !
b100 *
b100 /
b10000 %
b10000 )
b10000 5
b100 &
b100 '
b100 (
b11111111111111111111111111111111 6
13
11
b11 2
#5000
1"
1.
b101 !
b101 *
b101 /
b100000 %
b100000 )
b100000 5
b101 &
b101 '
b101 (
b11111111111111111111111111111111 6
13
11
b100 2
#6000
1"
1.
b110 !
b110 *
b110 /
b1000000 %
b1000000 )
b1000000 5
b110 &
b110 '
b110 (
b11111111111111111111111111111111 6
13
11
b101 2
#7000
1"
1.
b111 !
b111 *
b111 /
b10000000 %
b10000000 )
b10000000 5
b111 &
b111 '
b111 (
b11111111111111111111111111111111 6
13
11
b110 2
#8000
1#
1-
0"
0.
b0 !
b0 *
b0 /
b0 %
b0 )
b0 5
b1000 &
b1000 '
b1000 (
b11111111111111111111111111111111 6
13
11
b111 2
#9000
0#
0-
0$
b11111111 %
b11111111 )
04
b11111111 5
b1001 '
b1001 (
10
b11111111111111111111111111111111 6
03
01
b0 2
#10000
1"
1.
b101 !
b101 *
b101 /
1$
b100100 %
b100100 )
14
b100100 5
b0 &
b1010 '
b1010 (
00
#11000
1"
1.
b111 !
b111 *
b111 /
b10000001 %
b10000001 )
b10000001 5
b1 &
b1011 '
b1011 (
13
11
b101 2
b11111111111111111111111111111111 6
#12000
1"
1.
b11 !
b11 *
b11 /
b1001 %
b1001 )
b1001 5
b10 &
b1100 '
b1100 (
b11111111111111111111111111111111 6
13
11
b111 2
#13000
1"
1.
b110 !
b110 *
b110 /
b1100011 %
b1100011 )
b1100011 5
b11 &
b1101 '
b1101 (
b11111111111111111111111111111111 6
13
11
b11 2
#14000
1"
1.
b11 !
b11 *
b11 /
b1101 %
b1101 )
b1101 5
b100 &
b1110 '
b1110 (
b11111111111111111111111111111111 6
13
11
b110 2
#15000
1"
1.
b111 !
b111 *
b111 /
b10001101 %
b10001101 )
b10001101 5
b101 &
b1111 '
b1111 (
b11111111111111111111111111111111 6
13
11
b11 2
#16000
1"
1.
b110 !
b110 *
b110 /
b1100101 %
b1100101 )
b1100101 5
b110 &
b10000 '
b10000 (
b11111111111111111111111111111111 6
13
11
b111 2
#17000
1"
1.
b100 !
b100 *
b100 /
b10010 %
b10010 )
b10010 5
b111 &
b10001 '
b10001 (
b11111111111111111111111111111111 6
13
11
b110 2
#18000
1"
1.
b0 !
b0 *
b0 /
b1 %
b1 )
b1 5
b1000 &
b10010 '
b10010 (
b11111111111111111111111111111111 6
13
11
b100 2
#19000
b11 !
b11 *
b11 /
1"
1.
b1101 %
b1101 )
b1101 5
b1001 &
b10011 '
b10011 (
b11111111111111111111111111111111 6
13
11
b0 2
#20000
1"
1.
b110 !
b110 *
b110 /
b1110110 %
b1110110 )
b1110110 5
b1010 &
b10100 '
b10100 (
b11 2
b11111111111111111111111111111111 6
13
11
#21000
1"
1.
b101 !
b101 *
b101 /
b111101 %
b111101 )
b111101 5
b1011 &
b10101 '
b10101 (
b11111111111111111111111111111111 6
13
11
b110 2
#22000
1"
1.
b111 !
b111 *
b111 /
b11101101 %
b11101101 )
b11101101 5
b1100 &
b10110 '
b10110 (
b11111111111111111111111111111111 6
13
11
b101 2
#23000
1"
1.
b111 !
b111 *
b111 /
b10001100 %
b10001100 )
b10001100 5
b1101 &
b10111 '
b10111 (
b11111111111111111111111111111111 6
13
11
b111 2
#24000
1"
1.
b111 !
b111 *
b111 /
b11111001 %
b11111001 )
b11111001 5
b1110 &
b11000 '
b11000 (
b11111111111111111111111111111111 6
13
11
b111 2
#25000
1"
1.
b111 !
b111 *
b111 /
b11000110 %
b11000110 )
b11000110 5
b1111 &
b11001 '
b11001 (
b11111111111111111111111111111111 6
13
11
b111 2
#26000
1"
1.
b111 !
b111 *
b111 /
b11000101 %
b11000101 )
b11000101 5
b10000 &
b11010 '
b11010 (
b11111111111111111111111111111111 6
13
11
b111 2
#27000
1"
1.
b111 !
b111 *
b111 /
b10101010 %
b10101010 )
b10101010 5
b10001 &
b11011 '
b11011 (
b11111111111111111111111111111111 6
13
11
b111 2
#28000
1"
1.
b111 !
b111 *
b111 /
b11100101 %
b11100101 )
b11100101 5
b10010 &
b11100 '
b11100 (
b11111111111111111111111111111111 6
13
11
b111 2
#29000
1"
1.
b110 !
b110 *
b110 /
b1110111 %
b1110111 )
b1110111 5
b10011 &
b11101 '
b11101 (
b11111111111111111111111111111111 6
13
11
b111 2
#30000
b10100 &
b11110 '
b11110 (
b11111111111111111111111111111111 6
13
11
b110 2
