Module_2/Week_2/Tasks/Counter/counter.sv
//------------------------------------------------------------------------------
// Module: counter
// Description:
//   A synchronous parameterisable counter module with active-low
//   reset, enable, and up/down signals. The counter increments
//   when up_dn is HIGH and decrements when LOW.
//
// Author      : Muhammad Ahmed Qazi
// Date        : 2025-12-23
// Target      : FPGA
// Clocking    : <clk>, <posedge>
// Reset       : <async>, <active low>
//------------------------------------------------------------------------------

`timescale 1ns/1ps
module counter #(
    // Parameter declarations
    parameter integer COUNT_WIDTH = 16
)(
    // Port declarations
    input wire clk,
    input wire                      rst_n,
    input wire                      en,
    input wire                      up_dn,

    output reg [COUNT_WIDTH - 1: 0] count
);

    always @(posedge clk or negedge rst_n) begin
        if (!rst_n)
            count <= {COUNT_WIDTH{1'b0}};
        else if (en) begin
            if (up_dn) 
                count <= count + 1;       // increment
                // count <= count + {{(COUNT_WIDTH-1){1'b0}}, 1'b1};
            else 
                count <= count - 1;       // decrement
                // count <= count - {{(COUNT_WIDTH-1){1'b0}}, 1'b1};
        end
        // else: hold previous value
    end

endmodule

Module_2/Week_2/Tasks/Counter/counter_tb.sv
`timescale 1ns/1ps

module counter_tb;

    localparam int W = 8;

    // -------------------------
    // Signals
    // -------------------------
    logic clk;
    logic rst_n;
    logic en;
    logic up_dn;
    logic [W-1:0] count;

    // Reference model
    logic [W-1:0] ref_count;

    // -------------------------
    // DUT
    // -------------------------
    counter #(.COUNT_WIDTH(W)) dut (
        .clk   (clk),
        .rst_n (rst_n),
        .en    (en),
        .up_dn (up_dn),
        .count (count)
    );

    // -------------------------
    // Printing waveform
    // -------------------------
    initial begin
        $dumpfile("counter.vcd");
        $dumpvars(0, counter_tb);
    end

    // -------------------------
    // Clock
    // -------------------------
    always #5 clk <= ~clk;

    // -------------------------
    // Reset task
    // -------------------------
    task apply_reset;
    begin
        rst_n = 0;
        en = 0;
        up_dn = 0;
        ref_count = 0;
        repeat (2) @(posedge clk);
        rst_n = 1;
    end
    endtask

    // -------------------------
    // Driver tasks
    // -------------------------
    task count_up;
    begin
        @(posedge clk);
        en = 1;
        up_dn = 1;
    end
    endtask

    task count_down;
    begin
        @(posedge clk);
        en = 1;
        up_dn = 0;
    end
    endtask

    task hold;
    begin
        @(posedge clk);
        en = 0;
    end
    endtask

    // -------------------------
    // Reference model
    // -------------------------
    always @(posedge clk or negedge rst_n) begin
        if (!rst_n)
            ref_count <= 0;
        else if (en) begin
            if (up_dn)
                ref_count <= ref_count + 1;
            else
                ref_count <= ref_count - 1;
        end
    end

    // -------------------------
    // Monitor + checker
    // -------------------------
    always @(posedge clk or negedge rst_n) begin
        if (!rst_n) begin
            $display("T=%0t | RESET | count=%0d (expected 0)",
                    $time, count);
        end
        else if (count === ref_count) begin
            $display("T=%0t | PASS | en=%b up_dn=%b | count=%0d",
                    $time, en, up_dn, count);
        end
        else begin
            $display("T=%0t | FAIL | en=%b up_dn=%b | DUT=%0d REF=%0d Δ=%0d",
                    $time, en, up_dn, count, ref_count,
                    count - ref_count);
            $error("COUNTER MISMATCH");
        end
    end


    // -------------------------
    // Test sequence
    // -------------------------
    initial begin
        clk = 0;
        apply_reset();

        repeat (5) count_up();
        repeat (3) hold();
        repeat (2) count_down();

        #20;
        $finish;
    end

endmodule

Module_2/Week_2/Tasks/Counter/counter.vcd
$version Generated by VerilatedVcd $end
$timescale 1ps $end
 $scope module $rootio $end
 $upscope $end
 $scope module counter_tb $end
  $var wire 32 ) W [31:0] $end
  $var wire 1 # clk $end
  $var wire 1 $ rst_n $end
  $var wire 1 % en $end
  $var wire 1 & up_dn $end
  $var wire 8 ' count [7:0] $end
  $var wire 8 ( ref_count [7:0] $end
  $scope module dut $end
   $var wire 32 * COUNT_WIDTH [31:0] $end
   $var wire 1 # clk $end
   $var wire 1 $ rst_n $end
   $var wire 1 % en $end
   $var wire 1 & up_dn $end
   $var wire 8 ' count [7:0] $end
  $upscope $end
 $upscope $end
$enddefinitions $end


#0
0#
0$
0%
0&
b00000000 '
b00000000 (
b00000000000000000000000000001000 )
b00000000000000000000000000001000 *
#5000
1#
#10000
0#
#15000
1#
1$
#20000
0#
#25000
1#
1%
1&
b00000001 '
b00000001 (
#30000
0#
#35000
1#
b00000010 '
b00000010 (
#40000
0#
#45000
1#
b00000011 '
b00000011 (
#50000
0#
#55000
1#
b00000100 '
b00000100 (
#60000
0#
#65000
1#
b00000101 '
b00000101 (
#70000
0#
#75000
1#
0%
#80000
0#
#85000
1#
#90000
0#
#95000
1#
#100000
0#
#105000
1#
1%
0&
b00000100 '
b00000100 (
#110000
0#
#115000
1#
b00000011 '
b00000011 (
#120000
0#
#125000
1#
b00000010 '
b00000010 (
#130000
0#
#135000
1#
b00000001 '
b00000001 (
