Module_2/Week_2/Pipelined_Multipliers/Adder_Tree_Multiplier/adder_tree_multiplier.sv
//------------------------------------------------------------------------------
// Module: adder_tree_multiplier
// Description:
//   Implements a 8x8 pipelined combinational multiplier using an adder-tree architecture.
//   Partial products are generated in parallel and reduced through staged additions.
//   2-stage pipeline is employed for improved throughput.
//
// Author      : Muhammad Ahmed Qazi
// Date        : 2026-01-02
// Target      : FPGA
// Clocking    : <clk>, <posedge>
// Reset       : <async>, <active low>
//------------------------------------------------------------------------------

module adder_tree_multiplier #(
    // Parameter declarations
    parameter integer DATA_WIDTH = 8
)(
    // Port declarations


    // Port declarations
    input  wire                     clk,
    input  wire                     rst_n,

    input  wire                     EA,
    input  wire                     EB,
    input  wire                     start,
    input  wire [DATA_WIDTH-1:0]    A_in,
    input  wire [DATA_WIDTH-1:0]    B_in,

    output reg  [2*DATA_WIDTH-1:0]  P_out,
    output reg                      P_out_valid
);

    // ============================================================
    // Input registers
    // ============================================================
    reg [DATA_WIDTH-1:0] a_reg;
    reg [DATA_WIDTH-1:0] b_reg;

    always @(posedge clk or negedge rst_n) begin
        if (!rst_n) begin
            a_reg <= '0;
            b_reg <= '0;
        end else begin
            if (EA) a_reg <= A_in;
            if (EB) b_reg <= B_in;
        end
    end

    // ============================================================
    // Partial products (combinational)
    // ============================================================
    // Partial product (extended to 2N)
    wire [2*DATA_WIDTH-1:0] pp [DATA_WIDTH-1:0];

    genvar i;
    generate
        for (i = 0; i < DATA_WIDTH; i = i + 1) begin : GEN_PP
            assign pp[i] = b_reg[i] ? ({{DATA_WIDTH{1'b0}}, a_reg} << i)
                                    : {2*DATA_WIDTH{1'b0}};

        end
    endgenerate

    // ============================================================
    // Stage 1: First level of addition
    // ============================================================
    wire [2*DATA_WIDTH-1:0] sum_stage1 [((DATA_WIDTH+1)/2)-1:0];

    assign sum_stage1[0] = pp[0] + pp[1];
    assign sum_stage1[1] = pp[2] + pp[3];
    assign sum_stage1[2] = pp[4] + pp[5];
    assign sum_stage1[3] = pp[6] + pp[7];

    // ============================================================
    // Pipeline registers: sum_mid, valid_mid
    // ============================================================
    reg [2*DATA_WIDTH-1:0] sum_mid [((DATA_WIDTH+1)/2)-1:0];
    reg                    valid_mid;
    reg                    valid_out;

    always @(posedge clk or negedge rst_n) begin
        if (!rst_n) begin
            sum_mid[0] <= '0;
            sum_mid[1] <= '0;
            sum_mid[2] <= '0;
            sum_mid[3] <= '0;
            valid_mid  <= 1'b0;
            valid_out  <= 1'b0;
        end else begin
            sum_mid[0] <= sum_stage1[0];
            sum_mid[1] <= sum_stage1[1];
            sum_mid[2] <= sum_stage1[2];
            sum_mid[3] <= sum_stage1[3];
            valid_mid  <= start;
            valid_out  <= valid_mid;
        end
    end

    // ============================================================
    // Stage 2: Second level of addition
    // ============================================================
    wire [2*DATA_WIDTH-1:0] sum_stage2 [((DATA_WIDTH+3)/4)-1:0];

    assign sum_stage2[0] = sum_mid[0] + sum_mid[1];
    assign sum_stage2[1] = sum_mid[2] + sum_mid[3];

    // ============================================================
    // Output registers
    // ============================================================
    always @(posedge clk or negedge rst_n) begin
        if (!rst_n) begin
            P_out       <= '0;
            P_out_valid <= 1'b0;
        end else begin
            P_out       <= sum_stage2[0] + sum_stage2[1];
            P_out_valid <= valid_out;
        end
    end

endmodule

Module_2/Week_2/Pipelined_Multipliers/Adder_Tree_Multiplier/Archive/tb_multiplier.sv
/* verilator lint_off UNUSEDSIGNAL */
module tb_multiplier();

    // =========================================================================
    // SIGNAL DECLARATIONS
    // =========================================================================
    logic                  clk;
    logic                  rst_n;
    logic [7:0]            A_in;
    logic [7:0]            B_in;
    logic                  EA;
    logic                  EB;
    logic                  start;
    logic [15:0]           P_out;
    logic                  P_out_valid;
    
    // Scoreboard signals
    logic [15:0]           expected;
    logic [15:0]           p_val;
    logic [7:0]            a_val, b_val;
    
    // =========================================================================
    // QUEUE DECLARATIONS
    // =========================================================================
    logic [7:0] A_queue [$];
    logic [7:0] B_queue [$];
    
    // =========================================================================
    // PRINTING WAVEFORM
    // =========================================================================
    initial begin
        $dumpfile("tb_multiplier.vcd");
        $dumpvars(0, tb_multiplier);
    end
    
    // =========================================================================
    // DUT INSTANTIATION
    // =========================================================================
    `ifdef ARRAY_MULT
        array_multiplier #(
            .DATA_WIDTH(8)
        ) dut (
            .clk(clk),
            .rst_n(rst_n),
            .EA(EA),
            .EB(EB),
            .start(start),
            .A_in(A_in),
            .B_in(B_in),
            .P_out(P_out),
            .P_out_valid(P_out_valid)
        );
    `else
        adder_tree_multiplier #(
            .DATA_WIDTH(8)
        ) dut (
            .clk(clk),
            .rst_n(rst_n),
            .EA(EA),
            .EB(EB),
            .start(start),
            .A_in(A_in),
            .B_in(B_in),
            .P_out(P_out),
            .P_out_valid(P_out_valid)
        );
    `endif

    
    // =========================================================================
    // CLOCK GENERATION
    // =========================================================================
    initial begin
        clk = 0;
        forever #1 clk = ~clk;  // 10ns period
    end
    
    // =========================================================================
    // RESET SEQUENCE
    // =========================================================================
    initial begin
        rst_n = 0;
        repeat(3) @(posedge clk);
        rst_n = 1;
    end
    
    // =========================================================================
    // DRIVER PROCESS (Stimulus Application)
    // =========================================================================
    initial begin
        // Wait for reset to deassert
        @(posedge rst_n);
        
        // Test Vector 1: 10 * 15 = 150
        A_in = 8'd10;
        B_in = 8'd15;
        EA = 1;
        EB = 1;
        start = 1;
        A_queue.push_back(A_in);
        B_queue.push_back(B_in);
        @(negedge clk);
        EA = 0;
        EB = 0;
        start = 0;
        @(posedge clk);
        
        // Test Vector 2: 0 * 255 = 0 (boundary condition)
        A_in = 8'd0;
        B_in = 8'd255;
        EA = 1;
        EB = 1;
        start = 1;
        A_queue.push_back(A_in);
        B_queue.push_back(B_in);
        @(negedge clk);
        EA = 0;
        EB = 0;
        start = 0;
        @(posedge clk);
        
        // Test Vector 3: 255 * 255 = 65025 (max boundary)
        A_in = 8'd255;
        B_in = 8'd255;
        EA = 1;
        EB = 1;
        start = 1;
        A_queue.push_back(A_in);
        B_queue.push_back(B_in);
        @(negedge clk);
        EA = 0;
        EB = 0;
        start = 0;
        @(posedge clk);
        
        // Test Vector 4: 128 * 128 = 16384 (power of 2)
        A_in = 8'd128;
        B_in = 8'd128;
        EA = 1;
        EB = 1;
        start = 1;
        A_queue.push_back(A_in);
        B_queue.push_back(B_in);
        @(negedge clk);
        EA = 0;
        EB = 0;
        start = 0;
        @(posedge clk);
        
        // Signal end of test
        #100;
        $finish;
    end
    
    // =========================================================================
    // SCOREBOARD PROCESS (Self-Checking)
    // =========================================================================
    initial begin
        integer test_num = 0;

        // Wait for reset to deassert
        @(posedge rst_n);

        // Optional: let pipeline settle for a bit
        repeat (1) @(posedge clk);

        forever begin
            @(posedge clk);  // sample on clock edge

            // Only check when DUT says output is valid
            if (P_out_valid) begin
                if (A_queue.size() > 0 && B_queue.size() > 0) begin
                    // Pop corresponding input operands
                    a_val = A_queue.pop_front();
                    b_val = B_queue.pop_front();

                    // Compute expected result
                    expected = a_val * b_val;

                    // Sample DUT output
                    p_val = P_out;

                    // Compare and log
                    test_num = test_num + 1;
                    if (p_val == expected) begin
                        $display("[PASS] Test %0d: A=%3d, B=%3d | Expected=%5d, Got=%5d",
                                 test_num, a_val, b_val, expected, p_val);
                    end else begin
                        $display("[FAIL] Test %0d: A=%3d, B=%3d | Expected=%5d, Got=%5d",
                                 test_num, a_val, b_val, expected, p_val);
                    end
                end else begin
                    // No operands queued but DUT claims valid output
                    $display("[WARN] P_out_valid asserted but no queued inputs remain. P_out=%0d",
                             P_out);
                end
            end
        end
    end

    
endmodule

Module_2/Week_2/Pipelined_Multipliers/Adder_Tree_Multiplier/tb_multiplier.vcd
$version Generated by VerilatedVcd $end
$timescale 1ps $end
 $scope module $rootio $end
 $upscope $end
 $scope module tb_multiplier $end
  $var wire 1 E clk $end
  $var wire 1 F rst_n $end
  $var wire 8 # A_in [7:0] $end
  $var wire 8 $ B_in [7:0] $end
  $var wire 1 % EA $end
  $var wire 1 & EB $end
  $var wire 1 ' start $end
  $var wire 16 - P_out [15:0] $end
  $var wire 1 . P_out_valid $end
  $var wire 16 ( expected [15:0] $end
  $var wire 16 ) p_val [15:0] $end
  $var wire 8 * a_val [7:0] $end
  $var wire 8 + b_val [7:0] $end
  $scope module dut $end
   $var wire 32 G DATA_WIDTH [31:0] $end
   $var wire 1 E clk $end
   $var wire 1 F rst_n $end
   $var wire 1 % EA $end
   $var wire 1 & EB $end
   $var wire 1 ' start $end
   $var wire 8 # A_in [7:0] $end
   $var wire 8 $ B_in [7:0] $end
   $var wire 16 - P_out [15:0] $end
   $var wire 1 . P_out_valid $end
   $var wire 8 / a_reg [7:0] $end
   $var wire 8 0 b_reg [7:0] $end
   $var wire 16 1 pp[0] [15:0] $end
   $var wire 16 2 pp[1] [15:0] $end
   $var wire 16 3 pp[2] [15:0] $end
   $var wire 16 4 pp[3] [15:0] $end
   $var wire 16 5 pp[4] [15:0] $end
   $var wire 16 6 pp[5] [15:0] $end
   $var wire 16 7 pp[6] [15:0] $end
   $var wire 16 8 pp[7] [15:0] $end
   $var wire 16 9 sum_stage1[0] [15:0] $end
   $var wire 16 : sum_stage1[1] [15:0] $end
   $var wire 16 ; sum_stage1[2] [15:0] $end
   $var wire 16 < sum_stage1[3] [15:0] $end
   $var wire 16 = sum_mid[0] [15:0] $end
   $var wire 16 > sum_mid[1] [15:0] $end
   $var wire 16 ? sum_mid[2] [15:0] $end
   $var wire 16 @ sum_mid[3] [15:0] $end
   $var wire 1 A valid_mid $end
   $var wire 1 B valid_out $end
   $var wire 16 C sum_stage2[0] [15:0] $end
   $var wire 16 D sum_stage2[1] [15:0] $end
  $upscope $end
  $scope module unnamedblk1 $end
   $var wire 32 , test_num [31:0] $end
  $upscope $end
 $upscope $end
$enddefinitions $end


#0
b00000000 #
b00000000 $
0%
0&
0'
b0000000000000000 (
b0000000000000000 )
b00000000 *
b00000000 +
b00000000000000000000000000000000 ,
b0000000000000000 -
0.
b00000000 /
b00000000 0
b0000000000000000 1
b0000000000000000 2
b0000000000000000 3
b0000000000000000 4
b0000000000000000 5
b0000000000000000 6
b0000000000000000 7
b0000000000000000 8
b0000000000000000 9
b0000000000000000 :
b0000000000000000 ;
b0000000000000000 <
b0000000000000000 =
b0000000000000000 >
b0000000000000000 ?
b0000000000000000 @
0A
0B
b0000000000000000 C
b0000000000000000 D
0E
0F
b00000000000000000000000000001000 G
#1
1E
#2
0E
#3
1E
#4
0E
#5
b00001010 #
b00001111 $
1%
1&
1'
b00001010 /
b00001111 0
b0000000000001010 1
b0000000000010100 2
b0000000000101000 3
b0000000001010000 4
b0000000000011110 9
b0000000001111000 :
1A
1E
1F
#6
0%
0&
0'
0E
#7
b00000000 #
b11111111 $
1%
1&
1'
b00000000 /
b11111111 0
b0000000000000000 1
b0000000000000000 2
b0000000000000000 3
b0000000000000000 4
b0000000000000000 9
b0000000000000000 :
b0000000000011110 =
b0000000001111000 >
1B
b0000000010010110 C
1E
#8
0%
0&
0'
0E
#9
b11111111 #
1%
1&
1'
b0000000010010110 -
1.
b11111111 /
b0000000011111111 1
b0000000111111110 2
b0000001111111100 3
b0000011111111000 4
b0000111111110000 5
b0001111111100000 6
b0011111111000000 7
b0111111110000000 8
b0000001011111101 9
b0000101111110100 :
b0010111111010000 ;
b1011111101000000 <
b0000000000000000 =
b0000000000000000 >
b0000000000000000 C
1E
#10
0%
0&
0'
0E
#11
b10000000 #
b10000000 $
1%
1&
1'
b0000000010010110 (
b0000000010010110 )
b00001010 *
b00001111 +
b00000000000000000000000000000001 ,
b0000000000000000 -
b10000000 /
b10000000 0
b0000000000000000 1
b0000000000000000 2
b0000000000000000 3
b0000000000000000 4
b0000000000000000 5
b0000000000000000 6
b0000000000000000 7
b0100000000000000 8
b0000000000000000 9
b0000000000000000 :
b0000000000000000 ;
b0100000000000000 <
b0000001011111101 =
b0000101111110100 >
b0010111111010000 ?
b1011111101000000 @
b0000111011110001 C
b1110111100010000 D
1E
#12
0%
0&
0'
0E
#13
b0000000000000000 (
b0000000000000000 )
b00000000 *
b11111111 +
b00000000000000000000000000000010 ,
b1111111000000001 -
b0000000000000000 =
b0000000000000000 >
b0000000000000000 ?
b0100000000000000 @
0A
b0000000000000000 C
b0100000000000000 D
1E
#14
0E
#15
b1111111000000001 (
b1111111000000001 )
b11111111 *
b00000000000000000000000000000011 ,
b0100000000000000 -
0B
1E
#16
0E
#17
b0100000000000000 (
b0100000000000000 )
b10000000 *
b10000000 +
b00000000000000000000000000000100 ,
0.
1E
