Module_2/Week_1/Manchester_Encoder/manchesterMealy.sv
module manchesterMealy(w, clk, z);
    input w, clk;
    output z;

    reg z;
    reg [1:0] state, nextstate;

    initial begin
        state = 2'b00;
        nextstate = 2'b00;
        z = 1'b0;
    end

    always @(state, w) begin
        case (state)
            2'b00: begin
                if (w == 1'b0) begin
                    nextstate = 2'b01;
                    z = 1'b0;
                end else begin
                    nextstate = 2'b10;
                    z = 1'b1;
                end
            end
            2'b01: begin
                if (w == 1'b0) begin
                    nextstate = 2'b00;
                    z = 1'b1;
                end else begin
                    nextstate = 2'b10;
                    z = 1'b1;
                end
            end
            2'b10: begin
                if (w == 1'b0) begin
                    nextstate = 2'b01;
                    z = 1'b0;
                end else begin
                    nextstate = 2'b00;
                    z = 1'b0;
                end
            end
            default: begin
                nextstate = 2'b00;
                z = 1'b0;
            end
        endcase
    end

    always @(posedge clk) begin
        state <= nextstate;
    end

endmodule

Module 2/Week 1/Manchester Encoder/manchesterMealy_tb.sv
`timescale 1ns / 1ps

module tb_manchesterMealy;

    // Testbench signals
    reg  w;
    reg  clk;
    wire z;

    // Instantiate DUT
    manchesterMealy dut (
        .w(w),
        .clk(clk),
        .z(z)
    );

    // Printing waveform
    initial begin
        $dumpfile("manchesterMealy_tb.vcd");
        $dumpvars(0, tb_manchesterMealy);
    end

    // Clock generation: 10 ns period
    initial begin
        clk = 0;
        forever #5 clk = ~clk;
    end

    // Test sequence: 111001
    initial begin
        // Initialize
        w = 1;
        clk = 0;

        // Wait for some time before starting
        #5;

        // Apply bits (one bit per clock cycle)
        w = 1;  #20;   // bit 1
        w = 1;  #20;   // bit 1
        w = 1;  #20;   // bit 1
        w = 0;  #20;   // bit 0
        w = 0;  #20;   // bit 0
        w = 1;  #20;   // bit 1

        // Hold last value
        w = 0;
        #20;

        $finish;
    end

    // Optional monitoring
    initial begin
        $monitor("Time=%0t | clk=%b | w=%b | z=%b | state=%b",
                 $time, clk, w, z, dut.state);
    end

endmodule

Module 2/Week 1/Manchester Encoder/manchesterMealy_tb.vcd
$date
	Mon Dec 22 11:51:35 2025
$end
$version
	Icarus Verilog
$end
$timescale
	1ps
$end
$scope module tb_manchesterMealy $end
$var wire 1 ! z $end
$var reg 1 " clk $end
$var reg 1 # w $end
$scope module dut $end
$var wire 1 " clk $end
$var wire 1 # w $end
$var reg 2 $ nextstate [1:0] $end
$var reg 2 % state [1:0] $end
$var reg 1 ! z $end
$upscope $end
$upscope $end
$enddefinitions $end
$comment Show the parameter values. $end
$dumpall
$end
#0
$dumpvars
b0 %
b10 $
1#
0"
1!
$end
#5000
0!
b0 $
b10 %
1"
#10000
0"
#15000
1!
b10 $
b0 %
1"
#20000
0"
#25000
0!
b0 $
b10 %
1"
#30000
0"
#35000
1!
b10 $
b0 %
1"
#40000
0"
#45000
0!
b0 $
b10 %
1"
#50000
0"
#55000
1!
b10 $
b0 %
1"
#60000
0"
#65000
b1 %
1!
b0 $
1"
0#
#70000
0"
#75000
0!
b1 $
b0 %
1"
#80000
0"
#85000
1!
b0 $
b1 %
1"
#90000
0"
#95000
0!
b1 $
b0 %
1"
#100000
0"
#105000
b10 %
0!
b0 $
1"
1#
#110000
0"
#115000
1!
b10 $
b0 %
1"
#120000
0"
#125000
b1 %
1!
b0 $
1"
0#
#130000
0"
#135000
0!
b1 $
b0 %
1"
#140000
0"
#145000
1!
b0 $
b1 %
1"
